Workbook

Sheet Total
A1: RESUMO DE CUSTO / RECEITAS E RESULTADOS POR CONVÊNIO - ANO 2025
A3: JANEIRO | G3: ="INTERNAÇÕES - "& '[1]intern. diaria convenio'!$C$42 | K3: ="DIÁRIAS - " &'[1]intern. diaria convenio'!$C$88
A4: CONVENIO | B4: Diárias por Leito | F4: MAT / MED | H4: DIARIAS | J4: TAXAS | L4: TOTAL_CUSTO | M4: TOTAL_VENDA | N4: TOTAL
B5: PRIV. | C5: SEMI-P | D5: UTI | E5: UCTI | F5: CUSTO | G5: VENDA | H5: CUSTO | I5: VENDA | J5: CUSTO | K5: VENDA | L5: CUSTO | M5: VENDA | N5: RESULTADO
A6: ACORDO | C6: 27 | F6: 11696.8 | H6: 13973.75 | J6: 48166.66 | L6: =F6+H6+J6 | M6: 72162.5 | N6: =M6-L6
A7: ACORDO JUDICIAL | C7: 32 | D7: 10 | F7: 15775.74 | H7: 13590 | J7: 16128.63 | L7: =F7+H7+J7 | M7: 1 | N7: =M7-L7
A8: ASSEFAZ | L8: =F8+H8+J8 | M8: =G8+I8+K8 | N8: =M8-L8
A9: C.M.I | C9: 9 | F9: 2591.63 | H9: 5030.55 | J9: 13694.47 | L9: =F9+H9+J9 | M9: 13 | N9: =M9-L9
A10: CABERGS | C10: 7 | F10: 228.03 | G10: 3278.68 | H10: 3912.65 | I10: 2190.13 | J10: 887.92 | K10: 1165.13 | L10: =F10+H10+J10 | M10: =SUM(G10,I10,K10) | N10: =M10-L10
A11: CAIXA ECONOMICA FEDERAL | B11: 1 | F11: 23.74 | G11: 331.11 | H11: 573.45 | I11: 373.45 | J11: 0 | K11: 0 | L11: =F11+H11+J11 | M11: =SUM(G11,I11,K11) | N11: =M11-L11
A12: CASEMBRAPA | L12: =F12+H12+J12 | M12: =SUM(G12,I12,K12) | N12: =M12-L12
A13: CASSI | B13: 106 | D13: 33 | F13: 28398.98 | G13: 178239.55 | H13: 104095.7 | I13: 45377.24 | J13: 77955.84 | K13: 24775.21 | L13: =F13+H13+J13 | M13: =SUM(G13,I13,K13) | N13: =M13-L13
A14: CENTRO CLINICO GAUCHO | L14: =F14+H14+J14 | M14: =SUM(G14,I14,K14) | N14: =M14-L14
A15: EMBAIXADOR | L15: =F15+H15+J15 | M15: =SUM(G15,I15,K15) | N15: =M15-L15
A16: GEAP | B16: 23 | F16: 8805.24 | G16: 36537.54 | H16: 13104.25 | I16: 7874.28 | J16: 887.92 | K16: 1181.32 | L16: =F16+H16+J16 | M16: =SUM(G16,I16,K16) | N16: =M16-L16
A17: GRATUIDADE | F17: 5000 | G17: 3695 | H17: 0 | I17: 0 | J17: 0 | K17: 0 | L17: =F17+H17+J17 | M17: =SUM(G17,I17,K17) | N17: =M17-L17
A18: IPE | B18: 479 | C18: 201 | D18: 41 | E18: 34 | F18: 563440.48 | G18: 99896.3 | H18: 467905.76 | I18: 647539.13 | J18: 49155.33 | K18: 37808.16 | L18: =F18+H18+J18 | M18: =SUM(G18,I18,K18) | N18: =M18-L18
A19: IPE SEM PIN PAD | L19: =F19+H19+J19 | M19: =SUM(G19,I19,K19) | N19: =M19-L19
A20: IPIRANGA - SAMEISA | L20: =F20+H20+J20 | M20: =SUM(G20,I20,K20) | N20: =M20-L20
A21: PARTICULAR | B21: 50 | C21: 6 | F21: 22149.98 | G21: 49385.02 | H21: 31881.2 | I21: 23571 | J21: 34291.55 | K21: 32294.95 | L21: =F21+H21+J21 | M21: =SUM(G21,I21,K21) | N21: =M21-L21
A22: PETROBRAS | L22: =F22+H22+J22 | M22: =SUM(G22,I22,K22) | N22: =M22-L22
A23: POSTAL SAUDE | L23: =F23+H23+J23 | M23: =SUM(G23,I23,K23) | N23: =M23-L23
A24: SAUDE BRADESCO | F24: 44.83 | G24: 439.88 | H24: 0 | I24: 0 | J24: 494.61 | K24: 375.49 | L24: =F24+H24+J24 | M24: =SUM(G24,I24,K24) | N24: =M24-L24
A25: SAUDE MAIOR | C25: 262 | D25: 11 | E25: 5 | F25: 55196.29 | H25: 170855.6 | J25: 86197.28 | L25: =F25+H25+J25 | M25: 400000 | N25: =M25-L25
A26: SAUDE PAS MEDICINA | L26: =F26+H26+J26 | M26: =G26+I26+K26 | N26: =M26-L26
A27: SOCIOS | B27: 1 | C27: 12 | F27: 4419.35 | H27: 7280.85 | J27: 24802.51 | L27: =F27+H27+J27 | M27: 4460.7 | N27: =M27-L27
A28: SULAMERICA | L28: =F28+H28+J28 | M28: =G28+I28+K28 | N28: =M28-L28
A29: SUS | C29: 2432 | D29: 296 | E29: 198 | H29: 2209883 | L29: =F29+H29+J29 | M29: 2327154.3 | N29: =M29-L29
A30: TRANSPORTADORA FONSECA JUNIOR LTDA - EPP | L30: =F30+H30+J30 | M30: =G30+I30+K30 | N30: =M30-L30
A31: UNIMED | B31: 99 | C31: 131 | D31: 35 | E31: 32 | F31: 1595094.6 | G31: 79677.13 | H31: 222021.68 | I31: 234487.14 | J31: 24216.36 | K31: 48612.72 | L31: =F31+H31+J31 | M31: =SUM(G31,I31,K31) | N31: =M31-L31
A32: TOTAL | B32: =SUM(B6:B31) | C32: =SUM(C6:C31) | D32: =SUM(D6:D31) | E32: =SUM(E6:E31) | F32: =SUM(F6:F31) | G32: =SUM(G6:G31) | H32: =SUM(H6:H31) | I32: =SUM(I6:I31) | ... N32: =SUM(N6:N31)
A34: FEVEREIRO | G34: ="INTERNAÇÕES - "& '[1]intern. diaria convenio'!$D$42 | K34: ="DIÁRIAS - " &'[1]intern. diaria convenio'!$D$88
A35: CONVENIO | B35: Diárias por Leito | F35: MAT / MED | H35: DIARIAS | J35: TAXAS | L35: TOTAL_CUSTO | M35: TOTAL_VENDA | N35: TOTAL
B36: PRIV. | C36: SEMI-P | D36: UTI | E36: UCTI | F36: CUSTO | G36: VENDA | H36: CUSTO | I36: VENDA | J36: CUSTO | K36: VENDA | L36: CUSTO | M36: VENDA | N36: RESULTADO
A37: ACORDO | C37: 50 | E37: 4 | F37: 19777.44 | H37: 32394.31 | J37: 82180.8 | L37: =F37+H37+J37 | M37: 172252.5 | N37: =M37-L37
A38: ACORDO JUDICIAL | L38: =F38+H38+J38 | M38: 4102.5 | N38: =M38-L38
A39: ASSEFAZ | L39: =F39+H39+J39 | M39: =G39+I39+K39 | N39: =M39-L39
A40: C.M.I | C40: 1 | F40: 342.83 | H40: 558.95 | J40: 2361.11 | L40: =F40+H40+J40 | M40: 14 | N40: =M40-L40
A41: CABERGS | B41: 16 | F41: 2618.6 | G41: 28264.23 | H41: 8943.2 | I41: 8605.76 | J41: 22428.25 | K41: 5380.58 | L41: =F41+H41+J41 | M41: =SUM(G41,I41,K41) | N41: =M41-L41
A42: CAIXA ECONOMICA FEDERAL | L42: =F42+H42+J42 | M42: =SUM(G42,I42,K42) | N42: =M42-L42
A43: CASEMBRAPA | L43: =F43+H43+J43 | M43: =SUM(G43,I43,K43) | N43: =M43-L43
A44: CASSI | B44: 119 | D44: 3 | F44: 45624.17 | G44: 135206.32 | H44: 70592.05 | I44: 29278.84 | J44: 73502.04 | K44: 24350.01 | L44: =F44+H44+J44 | M44: =SUM(G44,I44,K44) | N44: =M44-L44
A45: CENTRO CLINICO GAUCHO | F45: 1496.66 | G45: 14120.11 | H45: 3353.7 | I45: 977.06 | J45: 9614.04 | K45: 6127.9 | L45: =F45+H45+J45 | M45: =SUM(G45,I45,K45) | N45: =M45-L45
A46: EMBAIXADOR | L46: =F46+H46+J46 | M46: =SUM(G46,I46,K46) | N46: =M46-L46
A47: GEAP | B47: 25 | F47: 779212.78 | G47: 40250.57 | H47: 14243.75 | I47: 8559 | J47: 18525.28 | K47: 5771.86 | L47: =F47+H47+J47 | M47: =SUM(G47,I47,K47) | N47: =M47-L47
A48: GRATUIDADE | F48: 45 | G48: 67.5 | H48: 0 | I48: 0 | J48: 0 | K48: 0 | L48: =F48+H48+J48 | M48: =SUM(G48,I48,K48) | N48: =M48-L48
A49: IPE | B49: 425 | C49: 100 | D49: 16 | E49: 4 | F49: 545586.35 | G49: 73954.88 | H49: 314713.11 | I49: 445611.5 | J49: 36842.8 | K49: 30101.97 | L49: =F49+H49+J49 | M49: =SUM(G49,I49,K49) | N49: =M49-L49
A50: IPE SEM PIN PAD | L50: =F50+H50+J50 | M50: =SUM(G50,I50,K50) | N50: =M50-L50
A51: IPIRANGA - SAMEISA | L51: =F51+H51+J51 | M51: =SUM(G51,I51,K51) | N51: =M51-L51
A52: PARTICULAR | B52: 33 | C52: 1 | F52: 41605.85 | G52: 19228.78 | H52: 24397.35 | I52: 18054 | J52: 9029.79 | K52: 14398.96 | L52: =F52+H52+J52 | M52: =SUM(G52,I52,K52) | N52: =M52-L52
A53: PETROBRAS | L53: =F53+H53+J53 | M53: =SUM(G53,I53,K53) | N53: =M53-L53
A54: POSTAL SAUDE | L54: =F54+H54+J54 | M54: =SUM(G54,I54,K54) | N54: =M54-L54
A55: SAUDE BRADESCO | B55: 2 | F55: 340.88 | G55: 4104.98 | H55: 1117.9 | I55: 481.62 | J55: 3305.56 | K55: 1719.78 | L55: =F55+H55+J55 | M55: =SUM(G55,I55,K55) | N55: =M55-L55
A56: SAUDE MAIOR | B56: 5 | C56: 238 | D56: 1 | E56: 28 | F56: 76064.36 | H56: 175153.17 | J56: 97069.57 | L56: =F56+H56+J56 | M56: 400000 | N56: =M56-L56
A57: SAUDE PAS MEDICINA | L57: =F57+H57+J57 | M57: =G57+I57+K57 | N57: =M57-L57
A58: SOCIOS | B58: 60 | D58: 7 | E58: 2 | F58: 5840.44 | H58: 69389.88 | J58: 22918.57 | L58: =F58+H58+J58 | M58: 1940.1 | N58: =M58-L58
A59: SULAMERICA | B59: 1 | F59: 1046.83 | G59: 6891.85 | H59: 573.45 | I59: 151.47 | J59: 2833.33 | K59: 770.21 | L59: =F59+H59+J59 | M59: =G59+I59+K59 | N59: =M59-L59
A60: SUS | C60: 2393 | D60: 240 | E60: 207 | H60: 2013681.8 | L60: =F60+H60+J60 | M60: 2398651.1 | N60: =M60-L60
A61: TRANSPORTADORA FONSECA JUNIOR LTDA - EPP | L61: =F61+H61+J61 | M61: =G61+I61+K61 | N61: =M61-L61
A62: UNIMED | B62: 124 | C62: 84 | D62: 12 | E62: 14 | F62: 229327.85 | G62: 26622.34 | H62: 145104.06 | I62: 139305.53 | J62: 14236.91 | K62: 18213.74 | L62: =F62+H62+J62 | M62: =SUM(G62,I62,K62) | N62: =M62-L62
A63: TOTAL | B63: =SUM(B37:B62) | C63: =SUM(C37:C62) | D63: =SUM(D37:D62) | E63: =SUM(E37:E62) | F63: =SUM(F37:F62) | G63: =SUM(G37:G62) | H63: =SUM(H37:H62) | I63: =SUM(I37:I62) | ... N63: =SUM(N37:N62)
A65: MARÇO | G65: ="INTERNAÇÕES - "& '[1]intern. diaria convenio'!$E$42 | K65: ="DIÁRIAS - " &'[1]intern. diaria convenio'!$E$88
A66: CONVENIO | B66: Diárias por Leito | F66: MAT / MED | H66: DIARIAS | J66: TAXAS | L66: TOTAL_CUSTO | M66: TOTAL_VENDA | N66: TOTAL
B67: PRIV. | C67: SEMI-P | D67: UTI | E67: UCTI | F67: CUSTO | G67: VENDA | H67: CUSTO | I67: VENDA | J67: CUSTO | K67: VENDA | L67: CUSTO | M67: VENDA | N67: RESULTADO
A68: ACORDO | C68: 54 | E68: 4 | F68: 21886.55 | H68: 35189.06 | J68: 84338.17 | L68: =F68+H68+J68 | M68: 149190 | N68: =M68-L68
A69: ACORDO JUDICIAL | L69: =F69+H69+J69 | M69: 0 | N69: =M69-L69
A70: ASSEFAZ | L70: =F70+H70+J70 | M70: =G70+I70+K70 | N70: =M70-L70
A71: C.M.I | C71: 4 | F71: 1280.87 | H71: 2235.8 | J71: 6138.89 | L71: =F71+H71+J71 | M71: 15 | N71: =M71-L71
A72: CABERGS | B72: 15 | F72: 7305.55 | G72: 27949.64 | H72: 8384.25 | I72: 8067.9 | J72: 1541.54 | K72: 2149.7 | L72: =F72+H72+J72 | M72: =SUM(G72,I72,K72) | N72: =M72-L72
A73: CAIXA ECONOMICA FEDERAL | L73: =F73+H73+J73 | M73: =SUM(G73,I73,K73) | N73: =M73-L73
A74: CASEMBRAPA | L74: =F74+H74+J74 | M74: =SUM(G74,I74,K74) | N74: =M74-L74
A75: CASSI | B75: 50 | F75: 47071.7 | G75: 105103.89 | H75: 36890.7 | I75: 15732 | J75: 53692.18 | K75: 22429.93 | L75: =F75+H75+J75 | M75: =SUM(G75,I75,K75) | N75: =M75-L75
A76: CENTRO CLINICO GAUCHO | F76: 602.24 | G76: 4609.17 | H76: 1132.4 | I76: 457.25 | J76: 4722.22 | K76: 1498.18 | L76: =F76+H76+J76 | M76: =SUM(G76,I76,K76) | N76: =M76-L76
A77: EMBAIXADOR | B77: 1 | F77: 328.95 | G77: 2391.57 | H77: 558.95 | I77: 189 | J77: 944.45 | K77: 751.96 | L77: =F77+H77+J77 | M77: =SUM(G77,I77,K77) | N77: =M77-L77
A78: GEAP | B78: 42 | F78: 192760.64 | G78: 70379.69 | H78: 23929.5 | I78: 14379.12 | J78: 14893.2 | K78: 4978.71 | L78: =F78+H78+J78 | M78: =SUM(G78,I78,K78) | N78: =M78-L78
A79: GRATUIDADE | F79: 16739.6 | G79: 5679.07 | H79: 558.95 | I79: 291 | J79: 0 | K79: 0 | L79: =F79+H79+J79 | M79: =SUM(G79,I79,K79) | N79: =M79-L79
A80: IPE | B80: 460 | C80: 205 | D80: 20 | E80: 6 | F80: 554286.54 | G80: 195849.51 | H80: 402539.84 | I80: 547531.13 | J80: 41276.52 | K80: 33686.76 | L80: =F80+H80+J80 | M80: =SUM(G80,I80,K80) | N80: =M80-L80
A81: IPE SEM PIN PAD | L81: =F81+H81+J81 | M81: =SUM(G81,I81,K81) | N81: =M81-L81
A82: IPIRANGA - SAMEISA | L82: =F82+H82+J82 | M82: =SUM(G82,I82,K82) | N82: =M82-L82
A83: PARTICULAR | B83: 84 | D83: 8 | F83: 21200.04 | G83: 67059.07 | H83: 58977.25 | I83: 46173 | J83: 20237.01 | K83: 36170.92 | L83: =F83+H83+J83 | M83: =SUM(G83,I83,K83) | N83: =M83-L83
A84: PETROBRAS | L84: =F84+H84+J84 | M84: =SUM(G84,I84,K84) | N84: =M84-L84
A85: POSTAL SAUDE | L85: =F85+H85+J85 | M85: =SUM(G85,I85,K85) | N85: =M85-L85
A86: SAUDE BRADESCO | B86: 1 | C86: 1 | F86: 1587.94 | G86: 5274.59 | H86: 1132.4 | I86: 431.1 | J86: 2326.97 | K86: 1444.29 | L86: =F86+H86+J86 | M86: =SUM(G86,I86,K86) | N86: =M86-L86
A87: SAUDE MAIOR | B87: 11 | C87: 330 | D87: 28 | E87: 6 | F87: 106300.25 | H87: 240643.09 | J87: 177387.54 | L87: =F87+H87+J87 | M87: 400000 | N87: =M87-L87
A88: SAUDE PAS MEDICINA | L88: =F88+H88+J88 | M88: =G88+I88+K88 | N88: =M88-L88
A89: SOCIOS | B89: 13 | D89: 1 | F89: 6455.07 | H89: 9960.75 | J89: 10574.53 | L89: =F89+H89+J89 | M89: 2591.8 | N89: =M89-L89
A90: SULAMERICA | L90: =F90+H90+J90 | M90: =G90+I90+K90 | N90: =M90-L90
A91: SUS | B91: 12 | C91: 2372 | D91: 162 | E91: 235 | H91: 1768065.9 | L91: =F91+H91+J91 | M91: 2329414.5 | N91: =M91-L91
A92: TRANSPORTADORA FONSECA JUNIOR LTDA - EPP | L92: =F92+H92+J92 | M92: =G92+I92+K92 | N92: =M92-L92
A93: UNIMED | B93: 213 | C93: 153 | D93: 21 | E93: 21 | F93: 484559.35 | G93: 79526.84 | H93: 265167.99 | I93: 261621.02 | J93: 34209.3 | K93: 52243.62 | L93: =F93+H93+J93 | M93: =SUM(G93,I93,K93) | N93: =M93-L93
A94: TOTAL | B94: =SUM(B68:B93) | C94: =SUM(C68:C93) | D94: =SUM(D68:D93) | E94: =SUM(E68:E93) | F94: =SUM(F68:F93) | G94: =SUM(G68:G93) | H94: =SUM(H68:H93) | I94: =SUM(I68:I93) | ... N94: =SUM(N68:N93)
A96: ABRIL | G96: ="INTERNAÇÕES - "& '[1]intern. diaria convenio'!$F$42 | K96: ="DIÁRIAS - " & '[1]intern. diaria convenio'!$F$88
A97: CONVENIO | B97: Diárias por Leito | F97: MAT / MED | H97: DIARIAS | J97: TAXAS | L97: TOTAL_CUSTO | M97: TOTAL_VENDA | N97: TOTAL
B98: PRIV. | C98: SEMI-P | D98: UTI | E98: UCTI | F98: CUSTO | G98: VENDA | H98: CUSTO | I98: VENDA | J98: CUSTO | K98: VENDA | L98: CUSTO | M98: VENDA | N98: RESULTADO
A99: ACORDO | C99: 54 | E99: 2 | F99: 31289.76 | H99: 32127.23 | J99: 81147.99 | L99: =F99+H99+J99 | M99: 176858 | N99: =M99-L99
A100: ACORDO JUDICIAL | L100: =F100+H100+J100 | M100: 0 | N100: =M100-L100
A101: ASSEFAZ | L101: =F101+H101+J101 | M101: =G101+I101+K101 | N101: =M101-L101
A102: C.M.I | C102: 1 | F102: 853.92 | H102: 558.95 | J102: 4250.01 | L102: =F102+H102+J102 | M102: 16 | N102: =M102-L102
A103: CABERGS | L103: =F103+H103+J103 | M103: =SUM(G103,I103,K103) | N103: =M103-L103
A104: CAIXA ECONOMICA FEDERAL | L104: =F104+H104+J104 | M104: =SUM(G104,I104,K104) | N104: =M104-L104
...

Sheet Acordo Judicial
A1: INTERNAÇÕES HOSPITALARES - ESTUDO CUSTO/RECEITA POR CONVÊNIO - ANO 2024
A3: ACORDO JUDICIAL
D5: INTERNAÇÕES - | G5: 0 | H5: DIÁRIAS - | J5: 0
A6: CONVÊNIO | C6: DIÁRIAS COBRADAS | G6: MAT/MED | I6: DIÁRIAS | K6: TAXAS | M6: TOTAL
C7: PRIV. | D7: SEMI-P | E7: UTI | F7: UCTI | G7: T. CUSTO | H7: T. VENDA | I7: T. CUSTO | J7: T. VENDA | K7: T. CUSTO | L7: T. VENDA | M7: T. CUSTO | N7: T. VENDA | O7: RESULTADO
A8: JANEIRO | C8: =Total!B7 | D8: =Total!C7 | E8: =Total!D7 | F8: =Total!E7 | G8: =Total!F7 | H8: =Total!G7 | I8: =Total!H7 | J8: =Total!I7 | ... O8: =Total!N7
A9: FEVEREIRO | C9: =Total!B38 | D9: =Total!C38 | E9: =Total!D38 | F9: =Total!E38 | G9: =Total!F38 | H9: =Total!G38 | I9: =Total!H38 | J9: =Total!I38 | ... O9: =Total!N38
A10: MARÇO | C10: =Total!B69 | D10: =Total!C69 | E10: =Total!D69 | F10: =Total!E69 | G10: =Total!F69 | H10: =Total!G69 | I10: =Total!H69 | J10: =Total!I69 | ... O10: =Total!N69
A11: ABRIL | C11: =Total!B100 | D11: =Total!C100 | E11: =Total!D100 | F11: =Total!E100 | G11: =Total!F100 | H11: =Total!G100 | I11: =Total!H100 | J11: =Total!I100 | ... O11: =Total!N100
A12: MAIO | C12: =Total!B131 | D12: =Total!C131 | E12: =Total!D131 | F12: =Total!E131 | G12: =Total!F131 | H12: =Total!G131 | I12: =Total!H131 | J12: =Total!I131 | ... O12: =Total!N131
A13: JUNHO | C13: =Total!B162 | D13: =Total!C162 | E13: =Total!D162 | F13: =Total!E162 | G13: =Total!F162 | H13: =Total!G162 | I13: =Total!H162 | J13: =Total!I162 | ... O13: =Total!N162
A14: JULHO | C14: =Total!B193 | D14: =Total!C193 | E14: =Total!D193 | F14: =Total!E193 | G14: =Total!F193 | H14: =Total!G193 | I14: =Total!H193 | J14: =Total!I193 | ... O14: =Total!N193
A15: AGOSTO | C15: =Total!B224 | D15: =Total!C224 | E15: =Total!D224 | F15: =Total!E224 | G15: =Total!F224 | H15: =Total!G224 | I15: =Total!H224 | J15: =Total!I224 | ... O15: =Total!N224
A16: SETEMBRO | C16: =Total!B255 | D16: =Total!C255 | E16: =Total!D255 | F16: =Total!E255 | G16: =Total!F255 | H16: =Total!G255 | I16: =Total!H255 | J16: =Total!I255 | ... O16: =Total!N255
A17: OUTUBRO | C17: =Total!B286 | D17: =Total!C286 | E17: =Total!D286 | F17: =Total!E286 | G17: =Total!F286 | H17: =Total!G286 | I17: =Total!H286 | J17: =Total!I286 | ... O17: =Total!N286
A18: NOVEMBRO | C18: =Total!B317 | D18: =Total!C317 | E18: =Total!D317 | F18: =Total!E317 | G18: =Total!F317 | H18: =Total!G317 | I18: =Total!H317 | J18: =Total!I317 | ... O18: =Total!N317
A19: DEZEMBRO | C19: =Total!B348 | D19: =Total!C348 | E19: =Total!D348 | F19: =Total!E348 | G19: =Total!F348 | H19: =Total!G348 | I19: =Total!H348 | J19: =Total!I348 | ... O19: =Total!N348
A20: Total | C20: =SUM(C8:C19) | D20: =SUM(D8:D19) | E20: =SUM(E8:E19) | F20: =SUM(F8:F19) | G20: =SUM(G8:G19) | H20: =SUM(H8:H19) | I20: =SUM(I8:I19) | J20: =SUM(J8:J19) | ... O20: =SUM(O8:O19)
B24: Dif: | G24: =SUM(C20:E20) | H24: =G24-J5

Sheet Acordo
A1: INTERNAÇÕES HOSPITALARES - ESTUDO CUSTO/RECEITA POR CONVÊNIO - ANO 2024
A3: ACORDO
D5: INTERNAÇÕES - | G5: ='[3]intern. diaria convenio'!$O$4 | H5: DIÁRIAS - | J5: ='[3]intern. diaria convenio'!$O$50
A6: CONVÊNIO | C6: DIÁRIAS COBRADAS | G6: MAT/MED | I6: DIÁRIAS | K6: TAXAS | M6: TOTAL
C7: PRIV. | D7: SEMI-P | E7: UTI | F7: UCTI | G7: T. CUSTO | H7: T. VENDA | I7: T. CUSTO | J7: T. VENDA | K7: T. CUSTO | L7: T. VENDA | M7: T. CUSTO | N7: T. VENDA | O7: RESULTADO
A8: JANEIRO | C8: =Total!B6 | D8: =Total!C6 | E8: =Total!D6 | F8: =Total!E6 | G8: =Total!F6 | H8: =Total!G6 | I8: =Total!H6 | J8: =Total!I6 | ... O8: =Total!N6
A9: FEVEREIRO | C9: =Total!B37 | D9: =Total!C37 | E9: =Total!D37 | F9: =Total!E37 | G9: =Total!F37 | H9: =Total!G37 | I9: =Total!H37 | J9: =Total!I37 | ... O9: =Total!N37
A10: MARÇO | C10: =Total!B68 | D10: =Total!C68 | E10: =Total!D68 | F10: =Total!E68 | G10: =Total!F68 | H10: =Total!G68 | I10: =Total!H68 | J10: =Total!I68 | ... O10: =Total!N68
A11: ABRIL | C11: =Total!B99 | D11: =Total!C99 | E11: =Total!D99 | F11: =Total!E99 | G11: =Total!F99 | H11: =Total!G99 | I11: =Total!H99 | J11: =Total!I99 | ... O11: =Total!N99
A12: MAIO | C12: =Total!B130 | D12: =Total!C130 | E12: =Total!D130 | F12: =Total!E130 | G12: =Total!F130 | H12: =Total!G130 | I12: =Total!H130 | J12: =Total!I130 | ... O12: =Total!N130
A13: JUNHO | C13: =Total!B161 | D13: =Total!C161 | E13: =Total!D161 | F13: =Total!E161 | G13: =Total!F161 | H13: =Total!G161 | I13: =Total!H161 | J13: =Total!I161 | ... O13: =Total!N161
A14: JULHO | C14: =Total!B192 | D14: =Total!C192 | E14: =Total!D192 | F14: =Total!E192 | G14: =Total!F192 | H14: =Total!G192 | I14: =Total!H192 | J14: =Total!I192 | ... O14: =Total!N192
A15: AGOSTO | C15: =Total!B223 | D15: =Total!C223 | E15: =Total!D223 | F15: =Total!E223 | G15: =Total!F223 | H15: =Total!G223 | I15: =Total!H223 | J15: =Total!I223 | ... O15: =Total!N223
A16: SETEMBRO | C16: =Total!B254 | D16: =Total!C254 | E16: =Total!D254 | F16: =Total!E254 | G16: =Total!F254 | H16: =Total!G254 | I16: =Total!H254 | J16: =Total!I254 | ... O16: =Total!N254
A17: OUTUBRO | C17: =Total!B285 | D17: =Total!C285 | E17: =Total!D285 | F17: =Total!E285 | G17: =Total!F285 | H17: =Total!G285 | I17: =Total!H285 | J17: =Total!I285 | ... O17: =Total!N285
A18: NOVEMBRO | C18: =Total!B316 | D18: =Total!C316 | E18: =Total!D316 | F18: =Total!E316 | G18: =Total!F316 | H18: =Total!G316 | I18: =Total!H316 | J18: =Total!I316 | ... O18: =Total!N316
A19: DEZEMBRO | C19: =Total!B347 | D19: =Total!C347 | E19: =Total!D347 | F19: =Total!E347 | G19: =Total!F347 | H19: =Total!G347 | I19: =Total!H347 | J19: =Total!I347 | ... O19: =Total!N347
A20: Total | C20: =SUM(C8:C19) | D20: =SUM(D8:D19) | E20: =SUM(E8:E19) | F20: =SUM(F8:F19) | G20: =SUM(G8:G19) | H20: =SUM(H8:H19) | I20: =SUM(I8:I19) | J20: =SUM(J8:J19) | ... O20: =SUM(O8:O19)
B24: Dif: | G24: =SUM(C20:E20) | H24: =G24-J5

Sheet C.M.I
A1: INTERNAÇÕES HOSPITALARES - ESTUDO CUSTO/RECEITA POR CONVÊNIO - ANO 2024
A3: C.M.I
D5: INTERNAÇÕES - | G5: ='[3]intern. diaria convenio'!$O$9 | H5: DIÁRIAS - | J5: ='[3]intern. diaria convenio'!$O$55
A6: CONVÊNIO | C6: DIÁRIAS COBRADAS | G6: MAT/MED | I6: DIÁRIAS | K6: TAXAS | M6: TOTAL
C7: PRIV. | D7: SEMI-P | E7: UTI | F7: UCTI | G7: T. CUSTO | H7: T. VENDA | I7: T. CUSTO | J7: T. VENDA | K7: T. CUSTO | L7: T. VENDA | M7: T. CUSTO | N7: T. VENDA | O7: RESULTADO
A8: JANEIRO | C8: =Total!B9 | D8: =Total!C9 | E8: =Total!D9 | F8: =Total!E9 | G8: =Total!F9 | H8: =Total!G9 | I8: =Total!H9 | J8: =Total!I9 | ... O8: =Total!N9
A9: FEVEREIRO | C9: =Total!B40 | D9: =Total!C40 | E9: =Total!D40 | F9: =Total!E40 | G9: =Total!F40 | H9: =Total!G40 | I9: =Total!H40 | J9: =Total!I40 | ... O9: =Total!N40
A10: MARÇO | C10: =Total!B71 | D10: =Total!C71 | E10: =Total!D71 | F10: =Total!E71 | G10: =Total!F71 | H10: =Total!G71 | I10: =Total!H71 | J10: =Total!I71 | ... O10: =Total!N71
A11: ABRIL | C11: =Total!B102 | D11: =Total!C102 | E11: =Total!D102 | F11: =Total!E102 | G11: =Total!F102 | H11: =Total!G102 | I11: =Total!H102 | J11: =Total!I102 | ... O11: =Total!N102
A12: MAIO | C12: =Total!B133 | D12: =Total!C133 | E12: =Total!D133 | F12: =Total!E133 | G12: =Total!F133 | H12: =Total!G133 | I12: =Total!H133 | J12: =Total!I133 | ... O12: =Total!N133
A13: JUNHO | C13: =Total!B164 | D13: =Total!C164 | E13: =Total!D164 | F13: =Total!E164 | G13: =Total!F164 | H13: =Total!G164 | I13: =Total!H164 | J13: =Total!I164 | ... O13: =Total!N164
A14: JULHO | C14: =Total!B195 | D14: =Total!C195 | E14: =Total!D195 | F14: =Total!E195 | G14: =Total!F195 | H14: =Total!G195 | I14: =Total!H195 | J14: =Total!I195 | ... O14: =Total!N195
A15: AGOSTO | C15: =Total!B226 | D15: =Total!C226 | E15: =Total!D226 | F15: =Total!E226 | G15: =Total!F226 | H15: =Total!G226 | I15: =Total!H226 | J15: =Total!I226 | ... O15: =Total!N226
A16: SETEMBRO | C16: =Total!B257 | D16: =Total!C257 | E16: =Total!D257 | F16: =Total!E257 | G16: =Total!F257 | H16: =Total!G257 | I16: =Total!H257 | J16: =Total!I257 | ... O16: =Total!N257
A17: OUTUBRO | C17: =Total!B288 | D17: =Total!C288 | E17: =Total!D288 | F17: =Total!E288 | G17: =Total!F288 | H17: =Total!G288 | I17: =Total!H288 | J17: =Total!I288 | ... O17: =Total!N288
A18: NOVEMBRO | C18: =Total!B319 | D18: =Total!C319 | E18: =Total!D319 | F18: =Total!E319 | G18: =Total!F319 | H18: =Total!G319 | I18: =Total!H319 | J18: =Total!I319 | ... O18: =Total!N319
A19: DEZEMBRO | C19: =Total!B350 | D19: =Total!C350 | E19: =Total!D350 | F19: =Total!E350 | G19: =Total!F350 | H19: =Total!G350 | I19: =Total!H350 | J19: =Total!I350 | ... O19: =Total!N350
A20: Total | C20: =SUM(C8:C19) | D20: =SUM(D8:D19) | E20: =SUM(E8:E19) | F20: =SUM(F8:F19) | G20: =SUM(G8:G19) | H20: =SUM(H8:H19) | I20: =SUM(I8:I19) | J20: =SUM(J8:J19) | ... O20: =SUM(O8:O19)

Sheet CABERGS
A1: INTERNAÇÕES HOSPITALARES - ESTUDO CUSTO/RECEITA POR CONVÊNIO - ANO 2024
A3: CABERGS
D5: INTERNAÇÕES - | G5: ='[3]intern. diaria convenio'!$O$10 | H5: DIÁRIAS - | J5: ='[3]intern. diaria convenio'!$O$56
A6: CONVÊNIO | C6: DIÁRIAS COBRADAS | G6: MAT/MED | I6: DIÁRIAS | K6: TAXAS | M6: TOTAL
C7: PRIV. | D7: SEMI-P | E7: UTI | F7: UCTI | G7: T. CUSTO | H7: T. VENDA | I7: T. CUSTO | J7: T. VENDA | K7: T. CUSTO | L7: T. VENDA | M7: T. CUSTO | N7: T. VENDA | O7: RESULTADO
A8: JANEIRO | C8: =Total!B10 | D8: =Total!C10 | E8: =Total!D10 | F8: =Total!E10 | G8: =Total!F10 | H8: =Total!G10 | I8: =Total!H10 | J8: =Total!I10 | ... O8: =Total!N10
A9: FEVEREIRO | C9: =Total!B41 | D9: =Total!C41 | E9: =Total!D41 | F9: =Total!E41 | G9: =Total!F41 | H9: =Total!G41 | I9: =Total!H41 | J9: =Total!I41 | ... O9: =Total!N41
A10: MARÇO | C10: =Total!B72 | D10: =Total!C72 | E10: =Total!D72 | F10: =Total!E72 | G10: =Total!F72 | H10: =Total!G72 | I10: =Total!H72 | J10: =Total!I72 | ... O10: =Total!N72
A11: ABRIL | C11: =Total!B103 | D11: =Total!C103 | E11: =Total!D103 | F11: =Total!E103 | G11: =Total!F103 | H11: =Total!G103 | I11: =Total!H103 | J11: =Total!I103 | ... O11: =Total!N103
A12: MAIO | C12: =Total!B134 | D12: =Total!C134 | E12: =Total!D134 | F12: =Total!E134 | G12: =Total!F134 | H12: =Total!G134 | I12: =Total!H134 | J12: =Total!I134 | ... O12: =Total!N134
A13: JUNHO | C13: =Total!B165 | D13: =Total!C165 | E13: =Total!D165 | F13: =Total!E165 | G13: =Total!F165 | H13: =Total!G165 | I13: =Total!H165 | J13: =Total!I165 | ... O13: =Total!N165
A14: JULHO | C14: =Total!B196 | D14: =Total!C196 | E14: =Total!D196 | F14: =Total!E196 | G14: =Total!F196 | H14: =Total!G196 | I14: =Total!H196 | J14: =Total!I196 | ... O14: =Total!N196
A15: AGOSTO | C15: =Total!B227 | D15: =Total!C227 | E15: =Total!D227 | F15: =Total!E227 | G15: =Total!F227 | H15: =Total!G227 | I15: =Total!H227 | J15: =Total!I227 | ... O15: =Total!N227
A16: SETEMBRO | C16: =Total!B258 | D16: =Total!C258 | E16: =Total!D258 | F16: =Total!E258 | G16: =Total!F258 | H16: =Total!G258 | I16: =Total!H258 | J16: =Total!I258 | ... O16: =Total!N258
A17: OUTUBRO | C17: =Total!B289 | D17: =Total!C289 | E17: =Total!D289 | F17: =Total!E289 | G17: =Total!F289 | H17: =Total!G289 | I17: =Total!H289 | J17: =Total!I289 | ... O17: =Total!N289
A18: NOVEMBRO | C18: =Total!B320 | D18: =Total!C320 | E18: =Total!D320 | F18: =Total!E320 | G18: =Total!F320 | H18: =Total!G320 | I18: =Total!H320 | J18: =Total!I320 | ... O18: =Total!N320
A19: DEZEMBRO | C19: =Total!B351 | D19: =Total!C351 | E19: =Total!D351 | F19: =Total!E351 | G19: =Total!F351 | H19: =Total!G351 | I19: =Total!H351 | J19: =Total!I351 | ... O19: =Total!N351
A20: Total | C20: =SUM(C8:C19) | D20: =SUM(D8:D19) | E20: =SUM(E8:E19) | F20: =SUM(F8:F19) | G20: =SUM(G8:G19) | H20: =SUM(H8:H19) | I20: =SUM(I8:I19) | J20: =SUM(J8:J19) | ... O20: =SUM(O8:O19)
B24: Dif: | G24: =SUM(C20:E20) | H24: =G24-J5

Sheet CAIXA ECONOMICA
A1: INTERNAÇÕES HOSPITALARES - ESTUDO CUSTO/RECEITA POR CONVÊNIO - ANO 2024
A3: CAIXA ECONOMICA FEDERAL
D5: INTERNAÇÕES - | G5: ='[3]intern. diaria convenio'!$O$8 | H5: DIÁRIAS - | J5: ='[3]intern. diaria convenio'!$O$54
A6: CONVÊNIO | C6: DIÁRIAS COBRADAS | G6: MAT/MED | I6: DIÁRIAS | K6: TAXAS | M6: TOTAL
C7: PRIV. | D7: SEMI-P | E7: UTI | F7: UCTI | G7: T. CUSTO | H7: T. VENDA | I7: T. CUSTO | J7: T. VENDA | K7: T. CUSTO | L7: T. VENDA | M7: T. CUSTO | N7: T. VENDA | O7: RESULTADO
A8: JANEIRO | C8: =Total!B11 | D8: =Total!C11 | E8: =Total!D11 | F8: =Total!E11 | G8: =Total!F11 | H8: =Total!G11 | I8: =Total!H11 | J8: =Total!I11 | ... O8: =Total!N11
A9: FEVEREIRO | C9: =Total!B42 | D9: =Total!C42 | E9: =Total!D42 | F9: =Total!E42 | G9: =Total!F12 | H9: =Total!G12 | I9: =Total!H12 | J9: =Total!I12 | K9: =Total!J12 | L9: =Total!K12 | M9: =Total!L12 | N9: =Total!M12 | O9: =Total!N12
A10: MARÇO | C10: =Total!B73 | D10: =Total!C73 | E10: =Total!D73 | F10: =Total!E73 | G10: =Total!F13 | H10: =Total!G13 | I10: =Total!H13 | J10: =Total!I13 | K10: =Total!J13 | L10: =Total!K13 | M10: =Total!L13 | N10: =Total!M13 | O10: =Total!N13
A11: ABRIL | C11: =Total!B104 | D11: =Total!C104 | E11: =Total!D104 | F11: =Total!E104 | G11: =Total!F14 | H11: =Total!G14 | I11: =Total!H14 | J11: =Total!I14 | K11: =Total!J14 | L11: =Total!K14 | M11: =Total!L14 | N11: =Total!M14 | O11: =Total!N14
A12: MAIO | C12: =Total!B135 | D12: =Total!C135 | E12: =Total!D135 | F12: =Total!E135 | G12: =Total!F15 | H12: =Total!G15 | I12: =Total!H15 | J12: =Total!I15 | K12: =Total!J15 | L12: =Total!K15 | M12: =Total!L15 | N12: =Total!M15 | O12: =Total!N15
A13: JUNHO | C13: =Total!B146 | D13: =Total!C146 | E13: =Total!D146 | F13: =Total!E146 | G13: =Total!F16 | H13: =Total!G16 | I13: =Total!H16 | J13: =Total!I16 | K13: =Total!J16 | L13: =Total!K16 | M13: =Total!L16 | N13: =Total!M16 | O13: =Total!N16
A14: JULHO | C14: =Total!B177 | D14: =Total!C177 | E14: =Total!D177 | F14: =Total!E177 | G14: =Total!F17 | H14: =Total!G17 | I14: =Total!H17 | J14: =Total!I17 | K14: =Total!J17 | L14: =Total!K17 | M14: =Total!L17 | N14: =Total!M17 | O14: =Total!N17
A15: AGOSTO | C15: =Total!B208 | D15: =Total!C208 | E15: =Total!D208 | F15: =Total!E208 | G15: =Total!F18 | H15: =Total!G18 | I15: =Total!H18 | J15: =Total!I18 | K15: =Total!J18 | L15: =Total!K18 | M15: =Total!L18 | N15: =Total!M18 | O15: =Total!N18
A16: SETEMBRO | C16: =Total!B239 | D16: =Total!C239 | E16: =Total!D239 | F16: =Total!E239 | G16: =Total!F19 | H16: =Total!G19 | I16: =Total!H19 | J16: =Total!I19 | K16: =Total!J19 | L16: =Total!K19 | M16: =Total!L19 | N16: =Total!M19 | O16: =Total!N19
A17: OUTUBRO | C17: =Total!B270 | D17: =Total!C270 | E17: =Total!D270 | F17: =Total!E270 | G17: =Total!F20 | H17: =Total!G20 | I17: =Total!H20 | J17: =Total!I20 | K17: =Total!J20 | L17: =Total!K20 | M17: =Total!L20 | N17: =Total!M20 | O17: =Total!N20
A18: NOVEMBRO | C18: =Total!B301 | D18: =Total!C301 | E18: =Total!D301 | F18: =Total!E301 | G18: =Total!F21 | H18: =Total!G21 | I18: =Total!H21 | J18: =Total!I21 | K18: =Total!J21 | L18: =Total!K21 | M18: =Total!L21 | N18: =Total!M21 | O18: =Total!N21
A19: DEZEMBRO | C19: =Total!B332 | D19: =Total!C332 | E19: =Total!D332 | F19: =Total!E332 | G19: =Total!F22 | H19: =Total!G22 | I19: =Total!H22 | J19: =Total!I22 | K19: =Total!J22 | L19: =Total!K22 | M19: =Total!L22 | N19: =Total!M22 | O19: =Total!N22
A20: Total | C20: =SUM(C8:C19) | D20: =SUM(D8:D19) | E20: =SUM(E8:E19) | F20: =SUM(F8:F19) | G20: =SUM(G8:G19) | H20: =SUM(H8:H19) | I20: =SUM(I8:I19) | J20: =SUM(J8:J19) | ... O20: =SUM(O8:O19)
B24: Dif: | G24: =SUM(C20:E20) | H24: =G24-J5

Sheet CASSI
A1: INTERNAÇÕES HOSPITALARES - ESTUDO CUSTO/RECEITA POR CONVÊNIO - ANO 2024
A3: CASSI
D5: INTERNAÇÕES - | G5: ='[3]intern. diaria convenio'!$O$12 | H5: DIÁRIAS - | J5: ='[3]intern. diaria convenio'!$O$58
A6: CONVÊNIO | C6: DIÁRIAS COBRADAS | G6: MAT/MED | I6: . | K6: TAXAS | M6: TOTAL
C7: PRIV. | D7: SEMI-P | E7: UTI | F7: UCTI | G7: T. CUSTO | H7: T. VENDA | I7: T. CUSTO | J7: T. VENDA | K7: T. CUSTO | L7: T. VENDA | M7: T. CUSTO | N7: T. VENDA | O7: RESULTADO
A8: JANEIRO | C8: =Total!B13 | D8: =Total!C13 | E8: =Total!D13 | F8: =Total!E13 | G8: =Total!F13 | H8: =Total!G13 | I8: =Total!H13 | J8: =Total!I13 | ... L8: =Total!K13 | M8: =K8+I8+G8 | N8: =Total!M13 | O8: =Total!N13
A9: FEVEREIRO | C9: =Total!B44 | D9: =Total!C44 | E9: =Total!D44 | F9: =Total!E44 | G9: =Total!F44 | H9: =Total!G44 | I9: =Total!H44 | J9: =Total!I44 | ... O9: =Total!N44
A10: MARÇO | C10: =Total!B75 | D10: =Total!C75 | E10: =Total!D75 | F10: =Total!E75 | G10: =Total!F75 | H10: =Total!G75 | I10: =Total!H75 | J10: =Total!I75 | ... O10: =Total!N75
A11: ABRIL | C11: =Total!B106 | D11: =Total!C106 | E11: =Total!D106 | F11: =Total!E106 | G11: =Total!F106 | H11: =Total!G106 | I11: =Total!H106 | J11: =Total!I106 | ... O11: =Total!N106
A12: MAIO | C12: =Total!B137 | D12: =Total!C137 | E12: =Total!D137 | F12: =Total!E137 | G12: =Total!F137 | H12: =Total!G137 | I12: =Total!H137 | J12: =Total!I137 | ... O12: =Total!N137
A13: JUNHO | C13: =Total!B168 | D13: =Total!C168 | E13: =Total!D168 | F13: =Total!E168 | G13: =Total!F168 | H13: =Total!G168 | I13: =Total!H168 | J13: =Total!I168 | ... O13: =Total!N168
A14: JULHO | C14: =Total!B199 | D14: =Total!C199 | E14: =Total!D199 | F14: =Total!E199 | G14: =Total!F199 | H14: =Total!G199 | I14: =Total!H199 | J14: =Total!I199 | ... O14: =Total!N199
A15: AGOSTO | C15: =Total!B230 | D15: =Total!C230 | E15: =Total!D230 | F15: =Total!E230 | G15: =Total!F230 | H15: =Total!G230 | I15: =Total!H230 | J15: =Total!I230 | ... O15: =Total!N230
A16: SETEMBRO | C16: =Total!B261 | D16: =Total!C261 | E16: =Total!D261 | F16: =Total!E261 | G16: =Total!F261 | H16: =Total!G261 | I16: =Total!H261 | J16: =Total!I261 | ... O16: =Total!N261
A17: OUTUBRO | C17: =Total!B292 | D17: =Total!C292 | E17: =Total!D292 | F17: =Total!E292 | G17: =Total!F292 | H17: =Total!G292 | I17: =Total!H292 | J17: =Total!I292 | ... O17: =Total!N292
A18: NOVEMBRO | C18: =Total!B323 | D18: =Total!C323 | E18: =Total!D323 | F18: =Total!E323 | G18: =Total!F323 | H18: =Total!G323 | I18: =Total!H323 | J18: =Total!I323 | ... O18: =Total!N323
A19: DEZEMBRO | C19: =Total!B354 | D19: =Total!C354 | E19: =Total!D354 | F19: =Total!E354 | G19: =Total!F354 | H19: =Total!G354 | I19: =Total!H354 | J19: =Total!I354 | ... O19: =Total!N354
A20: Total | C20: =SUM(C8:C19) | D20: =SUM(D8:D19) | E20: =SUM(E8:E19) | F20: =SUM(F8:F19) | G20: =SUM(G8:G19) | H20: =SUM(H8:H19) | I20: =SUM(I8:I19) | J20: =SUM(J8:J19) | ... O20: =SUM(O8:O19)
B24: Dif: | G24: =SUM(C20:E20) | H24: =G24-J5

Sheet EMBAIXADOR
A1: INTERNAÇÕES HOSPITALARES - ESTUDO CUSTO/RECEITA POR CONVÊNIO - ANO 2024
A3: EMBAIXADOR
D5: INTERNAÇÕES - | G5: ='[3]intern. diaria convenio'!$O$16 | H5: DIÁRIAS - | J5: ='[3]intern. diaria convenio'!$O$62
A6: CONVÊNIO | C6: DIÁRIAS COBRADAS | G6: MAT/MED | I6: DIÁRIAS | K6: TAXAS | M6: TOTAL
C7: PRIV. | D7: SEMI-P | E7: UTI | F7: UCTI | G7: T. CUSTO | H7: T. VENDA | I7: T. CUSTO | J7: T. VENDA | K7: T. CUSTO | L7: T. VENDA | M7: T. CUSTO | N7: T. VENDA | O7: RESULTADO
A8: JANEIRO | C8: =Total!B15 | D8: =Total!C15 | E8: =Total!D15 | F8: =Total!E15 | G8: =Total!F15 | H8: =Total!G15 | I8: =Total!H15 | J8: =Total!I15 | ... O8: =Total!N15
A9: FEVEREIRO | C9: =Total!B46 | D9: =Total!C46 | E9: =Total!D46 | F9: =Total!E46 | G9: =Total!J46 | H9: =Total!G46 | I9: =Total!H46 | J9: =Total!I46 | K9: =Total!J46 | L9: =Total!K46 | M9: =Total!L46 | N9: =Total!M46 | O9: =Total!N46
A10: MARÇO | C10: =Total!B77 | D10: =Total!C77 | E10: =Total!D77 | F10: =Total!E77 | G10: =Total!F77 | H10: =Total!G77 | I10: =Total!H77 | J10: =Total!I77 | ... O10: =Total!N77
A11: ABRIL | C11: =Total!B108 | D11: =Total!C108 | E11: =Total!D108 | F11: =Total!E108 | G11: =Total!F108 | H11: =Total!G108 | I11: =Total!H108 | J11: =Total!I108 | ... O11: =Total!N108
A12: MAIO | C12: =Total!B139 | D12: =Total!C139 | E12: =Total!D139 | F12: =Total!E139 | G12: =Total!F181 | H12: =Total!G139 | I12: =Total!H139 | J12: =Total!I139 | K12: =Total!J139 | L12: =Total!K139 | M12: =Total!L139 | N12: =Total!M139 | O12: =Total!N139
A13: JUNHO | C13: =Total!B170 | D13: =Total!C170 | E13: =Total!D170 | F13: =Total!E170 | G13: =Total!F170 | H13: =Total!G170 | I13: =Total!H170 | J13: =Total!I170 | ... O13: =Total!N170
A14: JULHO | C14: =Total!B201 | D14: =Total!C201 | E14: =Total!D201 | F14: =Total!E201 | G14: =Total!F201 | H14: =Total!G201 | I14: =Total!H201 | J14: =Total!I201 | ... O14: =Total!N201
A15: AGOSTO | C15: =Total!B232 | D15: =Total!C232 | E15: =Total!D232 | F15: =Total!E232 | G15: =Total!F232 | H15: =Total!G232 | I15: =Total!H232 | J15: =Total!I232 | ... O15: =Total!N232
A16: SETEMBRO | C16: =Total!B263 | D16: =Total!C263 | E16: =Total!D263 | F16: =Total!E263 | G16: =Total!F263 | H16: =Total!G263 | I16: =Total!H263 | J16: =Total!I263 | ... O16: =Total!N263
A17: OUTUBRO | C17: =Total!B294 | D17: =Total!C294 | E17: =Total!D294 | F17: =Total!E294 | G17: =Total!F294 | H17: =Total!G294 | I17: =Total!H294 | J17: =Total!I294 | ... O17: =Total!N294
A18: NOVEMBRO | C18: =Total!B325 | D18: =Total!C325 | E18: =Total!D325 | F18: =Total!E325 | G18: =Total!F325 | H18: =Total!G325 | I18: =Total!H325 | J18: =Total!I325 | ... O18: =Total!N325
A19: DEZEMBRO | C19: =Total!B356 | D19: =Total!C356 | E19: =Total!D356 | F19: =Total!E356 | G19: =Total!F356 | H19: =Total!G356 | I19: =Total!H356 | J19: =Total!I356 | ... O19: =Total!N356
A20: Total | C20: =SUM(C8:C19) | D20: =SUM(D8:D19) | E20: =SUM(E8:E19) | F20: =SUM(F8:F19) | G20: =SUM(G8:G19) | H20: =SUM(H8:H19) | I20: =SUM(I8:I19) | J20: =SUM(J8:J19) | ... O20: =SUM(O8:O19)
B24: Dif: | G24: =SUM(C20:E20) | H24: =G24-J5

Sheet GEAP
A1: INTERNAÇÕES HOSPITALARES - ESTUDO CUSTO/RECEITA POR CONVÊNIO - ANO 2024
A3: GEAP
D5: INTERNAÇÕES - | G5: ='[3]intern. diaria convenio'!$O$21 | H5: DIÁRIAS - | J5: ='[3]intern. diaria convenio'!$O$67
A6: CONVÊNIO | C6: DIÁRIAS COBRADAS | G6: MAT/MED | I6: DIÁRIAS | K6: TAXAS | M6: TOTAL
C7: PRIV. | D7: SEMI-P | E7: UTI | F7: UCTI | G7: T. CUSTO | H7: T. VENDA | I7: T. CUSTO | J7: T. VENDA | K7: T. CUSTO | L7: T. VENDA | M7: T. CUSTO | N7: T. VENDA | O7: RESULTADO
A8: JANEIRO | C8: =Total!B16 | D8: =Total!C16 | E8: =Total!D16 | F8: =Total!E16 | G8: =Total!F16 | H8: =Total!G16 | I8: =Total!H16 | J8: =Total!I16 | ... O8: =Total!N16
A9: FEVEREIRO | C9: =Total!B47 | D9: =Total!C47 | E9: =Total!D47 | F9: =Total!E47 | G9: =Total!F47 | H9: =Total!G47 | I9: =Total!H47 | J9: =Total!I47 | ... O9: =Total!N47
A10: MARÇO | C10: =Total!B78 | D10: =Total!C78 | E10: =Total!D78 | F10: =Total!E78 | G10: =Total!F78 | H10: =Total!G78 | I10: =Total!H78 | J10: =Total!I78 | ... O10: =Total!N78
A11: ABRIL | C11: =Total!B109 | D11: =Total!C109 | E11: =Total!D109 | F11: =Total!E109 | G11: =Total!F109 | H11: =Total!G109 | I11: =Total!H109 | J11: =Total!I109 | ... O11: =Total!N109
A12: MAIO | C12: =Total!B140 | D12: =Total!C140 | E12: =Total!D140 | F12: =Total!E140 | G12: =Total!F140 | H12: =Total!G140 | I12: =Total!H140 | J12: =Total!I140 | ... O12: =Total!N140
A13: JUNHO | C13: =Total!B171 | D13: =Total!C171 | E13: =Total!D171 | F13: =Total!E171 | G13: =Total!F171 | H13: =Total!G171 | I13: =Total!H171 | J13: =Total!I171 | ... O13: =Total!N171
A14: JULHO | C14: =Total!B202 | D14: =Total!C202 | E14: =Total!D202 | F14: =Total!E202 | G14: =Total!F202 | H14: =Total!G202 | I14: =Total!H202 | J14: =Total!I202 | ... O14: =Total!N202
A15: AGOSTO | C15: =Total!B233 | D15: =Total!C233 | E15: =Total!D233 | F15: =Total!E233 | G15: =Total!F233 | H15: =Total!G233 | I15: =Total!H233 | J15: =Total!I233 | ... O15: =Total!N233
A16: SETEMBRO | C16: =Total!B264 | D16: =Total!C264 | E16: =Total!D264 | F16: =Total!E264 | G16: =Total!F264 | H16: =Total!G264 | I16: =Total!H264 | J16: =Total!I264 | ... O16: =Total!N264
A17: OUTUBRO | C17: =Total!B295 | D17: =Total!C295 | E17: =Total!D295 | F17: =Total!E295 | G17: =Total!F295 | H17: =Total!G295 | I17: =Total!H295 | J17: =Total!I295 | ... O17: =Total!N295
A18: NOVEMBRO | C18: =Total!B326 | D18: =Total!C326 | E18: =Total!D326 | F18: =Total!E326 | G18: =Total!F326 | H18: =Total!G326 | I18: =Total!H326 | J18: =Total!I326 | ... O18: =Total!N326
A19: DEZEMBRO | C19: =Total!B357 | D19: =Total!C357 | E19: =Total!D357 | F19: =Total!E357 | G19: =Total!F357 | H19: =Total!G357 | I19: =Total!H357 | J19: =Total!I357 | ... O19: =Total!N357
A20: Total | C20: =SUM(C8:C19) | D20: =SUM(D8:D19) | E20: =SUM(E8:E19) | F20: =SUM(F8:F19) | G20: =SUM(G8:G19) | H20: =SUM(H8:H19) | I20: =SUM(I8:I19) | J20: =SUM(J8:J19) | ... O20: =SUM(O8:O19)
B24: Dif: | G24: =SUM(C20:E20) | H24: =G24-J5

Sheet IPE
A1: INTERNAÇÕES HOSPITALARES - ESTUDO CUSTO/RECEITA POR CONVÊNIO - ANO 2024
A3: IPE
D5: INTERNAÇÕES - | G5: ='[3]intern. diaria convenio'!$O$24 | H5: DIÁRIAS - | J5: ='[3]intern. diaria convenio'!$O$70
A6: CONVÊNIO | C6: DIÁRIAS COBRADAS | G6: MAT/MED | I6: DIÁRIAS | K6: TAXAS | M6: TOTAL
C7: PRIV. | D7: SEMI-P | E7: UTI | F7: UCTI | G7: T. CUSTO | H7: T. VENDA | I7: T. CUSTO | J7: T. VENDA | K7: T. CUSTO | L7: T. VENDA | M7: T. CUSTO | N7: T. VENDA | O7: RESULTADO
A8: JANEIRO | C8: =Total!B18 | D8: =Total!C18 | E8: =Total!D18 | F8: =Total!E18 | G8: =Total!F18 | H8: =Total!G18 | I8: =Total!H18 | J8: =Total!I18 | ... O8: =Total!N18
A9: FEVEREIRO | C9: =Total!B49 | D9: =Total!C49 | E9: =Total!D49 | F9: =Total!E49 | G9: =Total!F49 | H9: =Total!G49 | I9: =Total!H49 | J9: =Total!I49 | ... O9: =Total!N49
A10: MARÇO | C10: =Total!B80 | D10: =Total!C80 | E10: =Total!D80 | F10: =Total!E80 | G10: =Total!F80 | H10: =Total!G80 | I10: =Total!H80 | J10: =Total!I80 | ... O10: =Total!N80
A11: ABRIL | C11: =Total!B111 | D11: =Total!C111 | E11: =Total!D111 | F11: =Total!E111 | G11: =Total!F111 | H11: =Total!G111 | I11: =Total!H111 | J11: =Total!I111 | ... O11: =Total!N111
A12: MAIO | C12: =Total!B142 | D12: =Total!C142 | E12: =Total!D142 | F12: =Total!E142 | G12: =Total!F142 | H12: =Total!G142 | I12: =Total!H142 | J12: =Total!I142 | ... O12: =Total!N142
A13: JUNHO | C13: =Total!B173 | D13: =Total!C173 | E13: =Total!D173 | F13: =Total!E173 | G13: =Total!F173 | H13: =Total!G173 | I13: =Total!H173 | J13: =Total!I173 | ... O13: =Total!N173
A14: JULHO | C14: =Total!B204 | D14: =Total!C204 | E14: =Total!D204 | F14: =Total!E204 | G14: =Total!F204 | H14: =Total!G204 | I14: =Total!H204 | J14: =Total!I204 | ... O14: =Total!N204
A15: AGOSTO | C15: =Total!B235 | D15: =Total!C235 | E15: =Total!D235 | F15: =Total!E235 | G15: =Total!F235 | H15: =Total!G235 | I15: =Total!H235 | J15: =Total!I235 | ... O15: =Total!N235
A16: SETEMBRO | C16: =Total!B266 | D16: =Total!C266 | E16: =Total!D266 | F16: =Total!E266 | G16: =Total!F266 | H16: =Total!G266 | I16: =Total!H266 | J16: =Total!I266 | ... O16: =Total!N266
A17: OUTUBRO | C17: =Total!B297 | D17: =Total!C297 | E17: =Total!D297 | F17: =Total!E297 | G17: =Total!F297 | H17: =Total!G297 | I17: =Total!H297 | J17: =Total!I297 | ... O17: =Total!N297
A18: NOVEMBRO | C18: =Total!B328 | D18: =Total!C328 | E18: =Total!D328 | F18: =Total!E328 | G18: =Total!F328 | H18: =Total!G328 | I18: =Total!H328 | J18: =Total!I328 | ... O18: =Total!N328
A19: DEZEMBRO | C19: 489 | D19: 146 | E19: 20 | F19: 18 | G19: =Total!F359 | H19: =Total!G359 | I19: =Total!H359 | J19: =Total!I359 | K19: =Total!J359 | L19: =Total!K359 | M19: =Total!L359 | N19: =Total!M359 | O19: =Total!N359
A20: Total | C20: =SUM(C8:C19) | D20: =SUM(D8:D19) | E20: =SUM(E8:E19) | F20: =SUM(F8:F19) | G20: =SUM(G8:G19) | H20: =SUM(H8:H19) | I20: =SUM(I8:I19) | J20: =SUM(J8:J19) | ... O20: =SUM(O8:O19)
B24: Dif: | G24: =SUM(C20:E20) | H24: =G24-J5

Sheet IPE SEM PIN PAD
A1: INTERNAÇÕES HOSPITALARES - ESTUDO CUSTO/RECEITA POR CONVÊNIO - ANO 2023
A3: IPE SEM PIN PAD
D5: INTERNAÇÕES - | H5: DIÁRIAS -
A6: CONVÊNIO | C6: DIÁRIAS COBRADAS | G6: MAT/MED | I6: DIÁRIAS | K6: TAXAS | M6: TOTAL
C7: PRIV. | D7: SEMI-P | E7: UTI | F7: UCTI | G7: T. CUSTO | H7: T. VENDA | I7: T. CUSTO | J7: T. VENDA | K7: T. CUSTO | L7: T. VENDA | M7: T. CUSTO | N7: T. VENDA | O7: RESULTADO
A8: JANEIRO | C8: =Total!B19 | D8: =Total!C19 | E8: =Total!D19 | F8: =Total!E19 | G8: =Total!F19 | H8: =Total!G19 | I8: =Total!H19 | J8: =Total!I19 | ... O8: =Total!N19
A9: FEVEREIRO | C9: =Total!B50 | D9: =Total!C50 | E9: =Total!D50 | F9: =Total!E50 | G9: =Total!F50 | H9: =Total!G50 | I9: =Total!H50 | J9: =Total!I50 | ... O9: =Total!N50
A10: MARÇO | C10: =Total!B81 | D10: =Total!C81 | E10: =Total!D81 | F10: =Total!E81 | G10: =Total!F81 | H10: =Total!G81 | I10: =Total!H81 | J10: =Total!I81 | ... O10: =Total!N81
A11: ABRIL | C11: =Total!B112 | D11: =Total!C112 | E11: =Total!D112 | F11: =Total!E112 | G11: =Total!F112 | H11: =Total!G112 | I11: =Total!H112 | J11: =Total!I112 | ... O11: =Total!N112
A12: MAIO | C12: =Total!B143 | D12: =Total!C143 | E12: =Total!D143 | F12: =Total!E143 | G12: =Total!F143 | H12: =Total!G143 | I12: =Total!H143 | J12: =Total!I143 | ... O12: =Total!N143
A13: JUNHO | C13: =Total!B174 | D13: =Total!C174 | E13: =Total!D174 | F13: =Total!E174 | G13: =Total!F174 | H13: =Total!G174 | I13: =Total!H174 | J13: =Total!I174 | ... O13: =Total!N174
A14: JULHO | C14: =Total!B205 | D14: =Total!C205 | E14: =Total!D205 | F14: =Total!E205 | G14: =Total!F205 | H14: =Total!G205 | I14: =Total!H205 | J14: =Total!I205 | ... O14: =Total!N205
A15: AGOSTO | C15: =Total!B236 | D15: =Total!C236 | E15: =Total!D236 | F15: =Total!E236 | G15: =Total!F236 | H15: =Total!G236 | I15: =Total!H236 | J15: =Total!I236 | ... O15: =Total!N236
A16: SETEMBRO | C16: =Total!B267 | D16: =Total!C267 | E16: =Total!D267 | F16: =Total!E267 | G16: =Total!F267 | H16: =Total!G267 | I16: =Total!H267 | J16: =Total!I267 | ... O16: =Total!N267
A17: OUTUBRO | C17: =Total!B298 | D17: =Total!C298 | E17: =Total!D298 | F17: =Total!E298 | G17: =Total!F298 | H17: =Total!G298 | I17: =Total!H298 | J17: =Total!I298 | ... O17: =Total!N298
A18: NOVEMBRO | C18: =Total!B329 | D18: =Total!C329 | E18: =Total!D329 | F18: =Total!E329 | G18: =Total!F329 | H18: =Total!G329 | I18: =Total!H329 | J18: =Total!I329 | ... O18: =Total!N329
A19: DEZEMBRO | C19: =Total!B360 | D19: =Total!C360 | E19: =Total!D360 | F19: =Total!E360 | G19: =Total!F360 | H19: =Total!G360 | I19: =Total!H360 | J19: =Total!I360 | ... O19: =Total!N360
A20: Total | C20: =SUM(C8:C19) | D20: =SUM(D8:D19) | E20: =SUM(E8:E19) | F20: =SUM(F8:F19) | G20: =SUM(G8:G19) | H20: =SUM(H8:H19) | I20: =SUM(I8:I19) | J20: =SUM(J8:J19) | ... O20: =SUM(O8:O19)

Sheet PARTICULAR
A1: INTERNAÇÕES HOSPITALARES - ESTUDO CUSTO/RECEITA POR CONVÊNIO - ANO 2024
A3: PARTICULAR
D5: INTERNAÇÕES - | G5: ='[3]intern. diaria convenio'!$O$29 | H5: DIÁRIAS - | J5: ='[3]intern. diaria convenio'!$O$75
A6: CONVÊNIO | C6: DIÁRIAS COBRADAS | G6: MAT/MED | I6: DIÁRIAS | K6: TAXAS | M6: TOTAL
C7: PRIV. | D7: SEMI-P | E7: UTI | F7: UCTI | G7: T. CUSTO | H7: T. VENDA | I7: T. CUSTO | J7: T. VENDA | K7: T. CUSTO | L7: T. VENDA | M7: T. CUSTO | N7: T. VENDA | O7: RESULTADO
A8: JANEIRO | C8: =Total!B21 | D8: =Total!C21 | E8: =Total!D21 | F8: =Total!E21 | G8: =Total!F21 | H8: =Total!G21 | I8: =Total!H21 | J8: =Total!I21 | ... O8: =Total!N21
A9: FEVEREIRO | C9: =Total!B52 | D9: =Total!C52 | E9: =Total!D52 | F9: =Total!E52 | G9: =Total!F52 | H9: =Total!G52 | I9: =Total!H52 | J9: =Total!I52 | ... O9: =Total!N52
A10: MARÇO | C10: =Total!B83 | D10: =Total!C83 | E10: =Total!D83 | F10: =Total!E83 | G10: =Total!F83 | H10: =Total!G83 | I10: =Total!H83 | J10: =Total!I83 | ... O10: =Total!N83
A11: ABRIL | C11: =Total!B114 | D11: =Total!C114 | E11: =Total!D114 | F11: =Total!E114 | G11: =Total!F114 | H11: =Total!G114 | I11: =Total!H114 | J11: =Total!I114 | ... O11: =Total!N114
A12: MAIO | C12: =Total!B145 | D12: =Total!C145 | E12: =Total!D145 | F12: =Total!E145 | G12: =Total!F145 | H12: =Total!G145 | I12: =Total!H145 | J12: =Total!I145 | ... O12: =Total!N145
A13: JUNHO | C13: =Total!B176 | D13: =Total!C176 | E13: =Total!D176 | F13: =Total!E176 | G13: =Total!F176 | H13: =Total!G176 | I13: =Total!H176 | J13: =Total!I176 | ... O13: =Total!N176
A14: JULHO | C14: =Total!B207 | D14: =Total!C207 | E14: =Total!D207 | F14: =Total!E207 | G14: =Total!F207 | H14: =Total!G207 | I14: =Total!H207 | J14: =Total!I207 | ... O14: =Total!N207
A15: AGOSTO | C15: =Total!B238 | D15: =Total!C238 | E15: =Total!D238 | F15: =Total!E238 | G15: =Total!F238 | H15: =Total!G238 | I15: =Total!H238 | J15: =Total!I238 | ... O15: =Total!N238
A16: SETEMBRO | C16: =Total!B269 | D16: =Total!C269 | E16: =Total!D269 | F16: =Total!E269 | G16: =Total!F269 | H16: =Total!G269 | I16: =Total!H269 | J16: =Total!I269 | ... O16: =Total!N269
A17: OUTUBRO | C17: =Total!B300 | D17: =Total!C300 | E17: =Total!D300 | F17: =Total!E300 | G17: =Total!F300 | H17: =Total!G300 | I17: =Total!H300 | J17: =Total!I300 | ... O17: =Total!N300
A18: NOVEMBRO | C18: =Total!B331 | D18: =Total!C331 | E18: =Total!D331 | F18: =Total!E331 | G18: =Total!F331 | H18: =Total!G331 | I18: =Total!H331 | J18: =Total!I331 | ... O18: =Total!N331
A19: DEZEMBRO | C19: =Total!B362 | D19: =Total!C362 | E19: =Total!D362 | F19: =Total!E362 | G19: =Total!F362 | H19: =Total!G362 | I19: =Total!H362 | J19: =Total!I362 | ... O19: =Total!N362
A20: Total | C20: =SUM(C8:C19) | D20: =SUM(D8:D19) | E20: =SUM(E8:E19) | F20: =SUM(F8:F19) | G20: =SUM(G8:G19) | H20: =SUM(H8:H19) | I20: =SUM(I8:I19) | J20: =SUM(J8:J19) | ... O20: =SUM(O8:O19)
B24: Dif: | G24: =SUM(C20:E20) | H24: =G24-J5

Sheet SAUDE BRADESCO
A1: INTERNAÇÕES HOSPITALARES - ESTUDO CUSTO/RECEITA POR CONVÊNIO - ANO 2024
A3: SAUDE BRADESCO
D5: INTERNAÇÕES - | G5: ='[3]intern. diaria convenio'!$O$32 | H5: DIÁRIAS - | J5: ='[3]intern. diaria convenio'!$O$78
A6: CONVÊNIO | C6: DIÁRIAS COBRADAS | G6: MAT/MED | I6: DIÁRIAS | K6: TAXAS | M6: TOTAL
C7: PRIV. | D7: SEMI-P | E7: UTI | F7: UCTI | G7: T. CUSTO | H7: T. VENDA | I7: T. CUSTO | J7: T. VENDA | K7: T. CUSTO | L7: T. VENDA | M7: T. CUSTO | N7: T. VENDA | O7: RESULTADO
A8: JANEIRO | C8: =Total!B24 | D8: =Total!C24 | E8: =Total!D24 | F8: =Total!E24 | G8: =Total!F24 | H8: =Total!G24 | I8: =Total!H24 | J8: =Total!I24 | ... O8: =Total!N24
A9: FEVEREIRO | C9: =Total!B55 | D9: =Total!C55 | E9: =Total!D55 | F9: =Total!E55 | G9: =Total!F55 | H9: =Total!G55 | I9: =Total!H55 | J9: =Total!I55 | ... O9: =Total!N55
A10: MARÇO | C10: =Total!B86 | D10: =Total!C86 | E10: =Total!D86 | F10: =Total!E86 | G10: =Total!F86 | H10: =Total!G86 | I10: =Total!H86 | J10: =Total!I86 | ... O10: =Total!N86
A11: ABRIL | C11: =Total!B117 | D11: =Total!C117 | E11: =Total!D117 | F11: =Total!E117 | G11: =Total!F117 | H11: =Total!G117 | I11: =Total!H117 | J11: =Total!I117 | ... O11: =Total!N117
A12: MAIO | C12: =Total!B148 | D12: =Total!C148 | E12: =Total!D148 | F12: =Total!E148 | G12: =Total!F148 | H12: =Total!G148 | I12: =Total!H148 | J12: =Total!I148 | ... O12: =Total!N148
A13: JUNHO | C13: =Total!B179 | D13: =Total!C179 | E13: =Total!D179 | F13: =Total!E179 | G13: =Total!F179 | H13: =Total!G179 | I13: =Total!H179 | J13: =Total!I179 | ... O13: =Total!N179
A14: JULHO | C14: =Total!B210 | D14: =Total!C210 | E14: =Total!D210 | F14: =Total!E210 | G14: =Total!F210 | H14: =Total!G210 | I14: =Total!H210 | J14: =Total!I210 | ... O14: =Total!N210
A15: AGOSTO | C15: =Total!B241 | D15: =Total!C241 | E15: =Total!D241 | F15: =Total!E241 | G15: =Total!F241 | H15: =Total!G241 | I15: =Total!H241 | J15: =Total!I241 | ... O15: =Total!N241
A16: SETEMBRO | C16: =Total!B272 | D16: =Total!C272 | E16: =Total!D272 | F16: =Total!E272 | G16: =Total!F272 | H16: =Total!G272 | I16: =Total!H272 | J16: =Total!I272 | ... O16: =Total!N272
A17: OUTUBRO | C17: =Total!B303 | D17: =Total!C303 | E17: =Total!D303 | F17: =Total!E303 | G17: =Total!F303 | H17: =Total!G303 | I17: =Total!H303 | J17: =Total!I303 | ... O17: =Total!N303
A18: NOVEMBRO | C18: =Total!B334 | D18: =Total!C334 | E18: =Total!D334 | F18: =Total!E334 | G18: =Total!F334 | H18: =Total!G334 | I18: =Total!H334 | J18: =Total!I334 | ... O18: =Total!N334
A19: DEZEMBRO | C19: =Total!B365 | D19: =Total!C365 | E19: =Total!D365 | F19: =Total!E365 | G19: =Total!F365 | H19: =Total!G365 | I19: =Total!H365 | J19: =Total!I365 | ... O19: =Total!N365
A20: Total | C20: =SUM(C8:C19) | D20: =SUM(D8:D19) | E20: =SUM(E8:E19) | F20: =SUM(F8:F19) | G20: =SUM(G8:G19) | H20: =SUM(H8:H19) | I20: =SUM(I8:I19) | J20: =SUM(J8:J19) | ... O20: =SUM(O8:O19)
B24: Dif: | G24: =SUM(C20:E20) | H24: =G24-J5

Sheet SAUDE MAIOR
A1: INTERNAÇÕES HOSPITALARES - ESTUDO CUSTO/RECEITA POR CONVÊNIO - ANO 2024 | R1: INTERNAÇÕES HOSPITALARES - ESTUDO CUSTO/RECEITA POR CONVÊNIO - ANO 2023
A3: SAUDE MAIOR | R3: TOTAL SAUDE MAIOR (AMBULATORIAL + INTERNADOS)
D5: INTERNAÇÕES - | G5: ='[3]intern. diaria convenio'!$O$33 | H5: DIÁRIAS - | J5: ='[5]intern. diaria convenio'!$O$79 | U5: INTERNAÇÕES - | X5: =G5 | Y5: DIÁRIAS - | AA5: =J5
A6: CONVÊNIO | C6: DIÁRIAS COBRADAS | G6: MAT/MED | I6: DIÁRIAS | K6: TAXAS | M6: TOTAL | R6: CONVÊNIO | T6: DIÁRIAS COBRADAS | X6: MAT/MED | Z6: DIÁRIAS | AB6: TAXAS | AD6: TOTAL
C7: PRIV. | D7: SEMI-P | E7: UTI | F7: UCTI | G7: T. CUSTO | H7: T. VENDA | I7: T. CUSTO | J7: T. VENDA | K7: T. CUSTO | L7: T. VENDA | M7: T. CUSTO | N7: T. VENDA | O7: RESULTADO | T7: PRIV. | U7: SEMI-P | V7: UTI | W7: UCTI | X7: T. CUSTO | Y7: T. VENDA | Z7: T. CUSTO | AA7: T. VENDA | AB7: T. CUSTO | AC7: T. VENDA | AD7: T. CUSTO | AE7: T. VENDA | AF7: RESULTADO
A8: JANEIRO | C8: =Total!B25 | D8: =Total!C25 | E8: =Total!D25 | F8: =Total!E25 | G8: =Total!F25 | H8: =Total!G25 | I8: =Total!H25 | J8: =Total!I25 | ... O8: =Total!N25 | R8: JANEIRO | T8: =C8 | U8: =D8 | V8: =E8 | W8: =F8 | X8: =G8+'[6]SAUDE MAIOR'!C8 | Y8: =H8+'[6]SAUDE MAIOR'!$D8 | Z8: =I8 | AA8: =J8 | AB8: =K8+'[6]SAUDE MAIOR'!E8 | AC8: =L8+'[6]SAUDE MAIOR'!$F8 | AD8: =X8+Z8+AB8 | AE8: =370000+'[6]SAUDE MAIOR'!$H8 | AF8: =AE8-AD8
A9: FEVEREIRO | C9: =Total!B56 | D9: =Total!C56 | E9: =Total!D56 | F9: =Total!E56 | G9: =Total!F56 | H9: =Total!G56 | I9: =Total!H56 | J9: =Total!I56 | ... O9: =Total!N56 | R9: FEVEREIRO | T9: =C9 | U9: =D9 | V9: =E9 | W9: =F9 | X9: =G9+'[6]SAUDE MAIOR'!C9 | Y9: =H9+'[6]SAUDE MAIOR'!$D9 | Z9: =I9 | AA9: =J9 | AB9: =K9+'[6]SAUDE MAIOR'!E9 | AC9: =L9+'[6]SAUDE MAIOR'!$F9 | AD9: =X9+Z9+AB9 | AE9: =300000+'[6]SAUDE MAIOR'!$H9 | AF9: =AE9-AD9
A10: MARÇO | C10: =Total!B87 | D10: =Total!C87 | E10: =Total!D87 | F10: =Total!E87 | G10: =Total!F87 | H10: =Total!G87 | I10: =Total!H87 | J10: =Total!I87 | ... O10: =Total!N87 | R10: MARÇO | T10: =C10 | U10: =D10 | V10: =E10 | W10: =F10 | X10: =G10+'[6]SAUDE MAIOR'!C10 | Y10: =H10+'[6]SAUDE MAIOR'!$D10 | Z10: =I10 | AA10: =J10 | AB10: =K10+'[6]SAUDE MAIOR'!E10 | AC10: =L10+'[6]SAUDE MAIOR'!$F10 | AD10: =X10+Z10+AB10 | AE10: =300000+'[6]SAUDE MAIOR'!$H10 | AF10: =AE10-AD10
A11: ABRIL | C11: =Total!B118 | D11: =Total!C118 | E11: =Total!D118 | F11: =Total!E118 | G11: =Total!F118 | H11: =Total!G118 | I11: =Total!H118 | J11: =Total!I118 | ... O11: =Total!N118 | R11: ABRIL | T11: =C11 | U11: =D11 | V11: =E11 | W11: =F11 | X11: =G11+'[6]SAUDE MAIOR'!C11 | Y11: =H11+'[6]SAUDE MAIOR'!$D11 | Z11: =I11 | AA11: =J11 | AB11: =K11+'[6]SAUDE MAIOR'!E11 | AC11: =L11+'[6]SAUDE MAIOR'!$F11 | AD11: =X11+Z11+AB11 | AE11: =300000+'[6]SAUDE MAIOR'!$H11 | AF11: =AE11-AD11
A12: MAIO | C12: =Total!B149 | D12: =Total!C149 | E12: =Total!D149 | F12: =Total!E149 | G12: =Total!F149 | H12: =Total!G149 | I12: =Total!H149 | J12: =Total!I149 | ... O12: =Total!N149 | R12: MAIO | T12: =C12 | U12: =D12 | V12: =E12 | W12: =F12 | X12: =G12+'[6]SAUDE MAIOR'!C12 | Y12: =H12+'[6]SAUDE MAIOR'!$D12 | Z12: =I12 | AA12: =J12 | AB12: =K12+'[6]SAUDE MAIOR'!E12 | AC12: =L12+'[6]SAUDE MAIOR'!$F12 | AD12: =X12+Z12+AB12 | AE12: =300000+'[6]SAUDE MAIOR'!$H12 | AF12: =AE12-AD12
A13: JUNHO | C13: =Total!B180 | D13: =Total!C180 | E13: =Total!D180 | F13: =Total!E180 | G13: =Total!F180 | H13: =Total!G180 | I13: =Total!H180 | J13: =Total!I180 | ... O13: =Total!N180 | R13: JUNHO | T13: =C13 | U13: =D13 | V13: =E13 | W13: =F13 | X13: =G13+'[6]SAUDE MAIOR'!C13 | Y13: =H13+'[6]SAUDE MAIOR'!$D13 | Z13: =I13 | AA13: =J13 | AB13: =K13+'[6]SAUDE MAIOR'!E13 | AC13: =L13+'[6]SAUDE MAIOR'!$F13 | AD13: =X13+Z13+AB13 | AE13: =300000+'[6]SAUDE MAIOR'!$H13 | AF13: =AE13-AD13
A14: JULHO | C14: =Total!B211 | D14: =Total!C211 | E14: =Total!D211 | F14: =Total!E211 | G14: =Total!F211 | H14: =Total!G211 | I14: =Total!H211 | J14: =Total!I211 | ... O14: =Total!N211 | R14: JULHO | T14: =C14 | U14: =D14 | V14: =E14 | W14: =F14 | X14: =G14+'[6]SAUDE MAIOR'!C14 | Y14: =H14+'[6]SAUDE MAIOR'!$D14 | Z14: =I14 | AA14: =J14 | AB14: =K14+'[6]SAUDE MAIOR'!E14 | AC14: =L14+'[6]SAUDE MAIOR'!$F14 | AD14: =X14+Z14+AB14 | AE14: =300000+'[6]SAUDE MAIOR'!$H14 | AF14: =AE14-AD14
A15: AGOSTO | C15: =Total!B242 | D15: =Total!C242 | E15: =Total!D242 | F15: =Total!E242 | G15: =Total!F242 | H15: =Total!G242 | I15: =Total!H242 | J15: =Total!I242 | ... O15: =Total!N242 | R15: AGOSTO | T15: =C15 | U15: =D15 | V15: =E15 | W15: =F15 | X15: =G15+'[6]SAUDE MAIOR'!C15 | Y15: =H15+'[6]SAUDE MAIOR'!$D15 | Z15: =I15 | AA15: =J15 | AB15: =K15+'[6]SAUDE MAIOR'!E15 | AC15: =L15+'[6]SAUDE MAIOR'!$F15 | AD15: =X15+Z15+AB15 | AE15: =300000+'[6]SAUDE MAIOR'!$H15 | AF15: =AE15-AD15
A16: SETEMBRO | C16: =Total!B273 | D16: =Total!C273 | E16: =Total!D273 | F16: =Total!E273 | G16: =Total!F273 | H16: =Total!G273 | I16: =Total!H273 | J16: =Total!I273 | ... O16: =Total!N273 | R16: SETEMBRO | T16: =C16 | U16: =D16 | V16: =E16 | W16: =F16 | X16: =G16+'[6]SAUDE MAIOR'!C16 | Y16: =H16+'[6]SAUDE MAIOR'!$D16 | Z16: =I16 | AA16: =J16 | AB16: =K16+'[6]SAUDE MAIOR'!E16 | AC16: =L16+'[6]SAUDE MAIOR'!$F16 | AD16: =X16+Z16+AB16 | AE16: =300000+'[6]SAUDE MAIOR'!$H16 | AF16: =AE16-AD16
A17: OUTUBRO | C17: =Total!B304 | D17: =Total!C304 | E17: =Total!D304 | F17: =Total!E304 | G17: =Total!F304 | H17: =Total!G304 | I17: =Total!H304 | J17: =Total!I304 | ... O17: =Total!N304 | R17: OUTUBRO | T17: =C17 | U17: =D17 | V17: =E17 | W17: =F17 | X17: =G17+'[6]SAUDE MAIOR'!C17 | Y17: =H17+'[6]SAUDE MAIOR'!$D17 | Z17: =I17 | AA17: =J17 | AB17: =K17+'[6]SAUDE MAIOR'!E17 | AC17: =L17+'[6]SAUDE MAIOR'!$F17 | AD17: =X17+Z17+AB17 | AE17: =300000+'[6]SAUDE MAIOR'!$H17 | AF17: =AE17-AD17
A18: NOVEMBRO | C18: =Total!B335 | D18: =Total!C335 | E18: =Total!D335 | F18: =Total!E335 | G18: =Total!F335 | H18: =Total!G335 | I18: =Total!H335 | J18: =Total!I335 | ... O18: =Total!N335 | R18: NOVEMBRO | T18: =C18 | U18: =D18 | V18: =E18 | W18: =F18 | X18: =G18+'[6]SAUDE MAIOR'!C18 | Y18: =H18+'[6]SAUDE MAIOR'!$D18 | Z18: =I18 | AA18: =J18 | AB18: =K18+'[6]SAUDE MAIOR'!E18 | AC18: =L18+'[6]SAUDE MAIOR'!$F18 | AD18: =X18+Z18+AB18 | AE18: =300000+'[6]SAUDE MAIOR'!$H18 | AF18: =AE18-AD18
A19: DEZEMBRO | C19: =Total!B366 | D19: =Total!C366 | E19: =Total!D366 | F19: =Total!E366 | G19: =Total!F366 | H19: =Total!G366 | I19: =Total!H366 | J19: =Total!I366 | ... O19: =Total!N366 | R19: DEZEMBRO | T19: =C19 | U19: =D19 | V19: =E19 | W19: =F19 | X19: =G19+'[6]SAUDE MAIOR'!C19 | Y19: =H19+'[6]SAUDE MAIOR'!$D19 | Z19: =I19 | AA19: =J19 | AB19: =K19+'[6]SAUDE MAIOR'!E19 | AC19: =L19+'[6]SAUDE MAIOR'!$F19 | AD19: =X19+Z19+AB19 | AE19: =300000+'[6]SAUDE MAIOR'!$H19 | AF19: =AE19-AD19
A20: Total | C20: =SUM(C8:C19) | D20: =SUM(D8:D19) | E20: =SUM(E8:E19) | F20: =SUM(F8:F19) | G20: =SUM(G8:G19) | H20: =SUM(H8:H19) | I20: =SUM(I8:I19) | J20: =SUM(J8:J19) | ... O20: =SUM(O8:O19) | R20: Total | T20: 54 | U20: 1139 | V20: 176 | W20: 0 | X20: =SUM(X8:X19) | Y20: =SUM(Y8:Y19) | Z20: =SUM(Z8:Z19) | AA20: =SUM(AA8:AA19) | AB20: 107358.29 | AC20: =SUM(AC8:AC19) | AD20: =SUM(AD8:AD19) | AE20: =SUM(AE8:AE19) | AF20: =AE20-AD20
G23: SAUDE MAIOR INTERNADO - Janeiro 2024 a Dezembro 2024 | X23: TOTAL SAUDE MAIOR (AMBULATORIO/INTERNADO) - Janeiro 2023 a Dezembro 2023
G24: MAT/MED | I24: DIÁRIAS | K24: TAXAS | M24: TOTAL | X24: MAT/MED | Z24: DIÁRIAS | AB24: TAXAS | AD24: TOTAL
G25: T. CUSTO | H25: T. VENDA | I25: T. CUSTO | J25: T. VENDA | K25: T. CUSTO | L25: T. VENDA | M25: T. CUSTO | N25: T. VENDA | O25: RESULTADO | X25: T. CUSTO | Y25: T. VENDA | Z25: T. CUSTO | AA25: T. VENDA | AB25: T. CUSTO | AC25: T. VENDA | AD25: T. CUSTO | AE25: T. VENDA | AF25: RESULTADO
G26: =G20 | H26: =H20 | I26: =I20 | J26: =J20 | K26: =K20 | L26: =L20 | M26: =M20 | N26: =N20 | O26: =O20 | X26: =X20 | Y26: =Y20 | Z26: =Z20 | AA26: =AA20 | AB26: =AB20 | AC26: =AC20 | AD26: =AD20 | AE26: =AE20 | AF26: =AF20
M27: =M20 | N27: =H20+J20+L20 | O27: =N27-M26 | AD27: =AD20 | AE27: =Y20+AA20+AC20 | AF27: =AE27-AD26

Sheet SOCIOS
A1: INTERNAÇÕES HOSPITALARES - ESTUDO CUSTO/RECEITA POR CONVÊNIO - ANO 2024
A3: SOCIOS
D5: INTERNAÇÕES - | G5: ='[3]intern. diaria convenio'!$O$35 | H5: DIÁRIAS - | J5: ='[3]intern. diaria convenio'!$O$81
A6: CONVÊNIO | C6: DIÁRIAS COBRADAS | G6: MAT/MED | I6: DIÁRIAS | K6: TAXAS | M6: TOTAL
C7: PRIV. | D7: SEMI-P | E7: UTI | F7: UCTI | G7: T. CUSTO | H7: T. VENDA | I7: T. CUSTO | J7: T. VENDA | K7: T. CUSTO | L7: T. VENDA | M7: T. CUSTO | N7: T. VENDA | O7: RESULTADO
A8: JANEIRO | C8: =Total!B27 | D8: =Total!C27 | E8: =Total!D27 | F8: =Total!E27 | G8: =Total!F27 | H8: =Total!G27 | I8: =Total!H27 | J8: =Total!I27 | ... O8: =Total!N27
A9: FEVEREIRO | C9: =Total!B58 | D9: =Total!C58 | E9: =Total!D58 | F9: =Total!E58 | G9: =Total!F58 | H9: =Total!G58 | I9: =Total!H58 | J9: =Total!I58 | ... O9: =Total!N58
A10: MARÇO | C10: =Total!B89 | D10: =Total!C89 | E10: =Total!D89 | F10: =Total!E89 | G10: =Total!F89 | H10: =Total!G89 | I10: =Total!H89 | J10: =Total!I89 | ... O10: =Total!N89
A11: ABRIL | C11: =Total!B120 | D11: =Total!C120 | E11: =Total!D120 | F11: =Total!E120 | G11: =Total!F120 | H11: =Total!G120 | I11: =Total!H120 | J11: =Total!I120 | ... O11: =Total!N120
A12: MAIO | C12: =Total!B151 | D12: =Total!C151 | E12: =Total!D151 | F12: =Total!E151 | G12: =Total!F151 | H12: =Total!G151 | I12: =Total!H151 | J12: =Total!I151 | ... O12: =Total!N151
A13: JUNHO | C13: =Total!B182 | D13: =Total!C182 | E13: =Total!D182 | F13: =Total!E182 | G13: =Total!F182 | H13: =Total!G182 | I13: =Total!H182 | J13: =Total!I182 | ... O13: =Total!N182
A14: JULHO | C14: =Total!B213 | D14: =Total!C213 | E14: =Total!D213 | F14: =Total!E213 | G14: =Total!F213 | H14: =Total!G213 | I14: =Total!H213 | J14: =Total!I213 | ... O14: =Total!N213
A15: AGOSTO | C15: =Total!B244 | D15: =Total!C244 | E15: =Total!D244 | F15: =Total!E244 | G15: =Total!F244 | H15: =Total!G244 | I15: =Total!H244 | J15: =Total!I244 | ... O15: =Total!N244
A16: SETEMBRO | C16: =Total!B275 | D16: =Total!C275 | E16: =Total!D275 | F16: =Total!E275 | G16: =Total!F275 | H16: =Total!G275 | I16: =Total!H275 | J16: =Total!I275 | ... O16: =Total!N275
A17: OUTUBRO | C17: =Total!B306 | D17: =Total!C306 | E17: =Total!D306 | F17: =Total!E306 | G17: =Total!F306 | H17: =Total!G306 | I17: =Total!H306 | J17: =Total!I306 | ... O17: =Total!N306
A18: NOVEMBRO | C18: =Total!B337 | D18: =Total!C337 | E18: =Total!D337 | F18: =Total!E337 | G18: =Total!F337 | H18: =Total!G337 | I18: =Total!H337 | J18: =Total!I337 | ... O18: =Total!N337
A19: DEZEMBRO | C19: =Total!B368 | D19: =Total!C368 | E19: =Total!D368 | F19: =Total!E368 | G19: =Total!F368 | H19: =Total!G368 | I19: =Total!H368 | J19: =Total!I368 | ... O19: =Total!N368
A20: Total | C20: =SUM(C8:C19) | D20: =SUM(D8:D19) | E20: =SUM(E8:E19) | F20: =SUM(F8:F19) | G20: =SUM(G8:G19) | H20: =SUM(H8:H19) | I20: =SUM(I8:I19) | J20: =SUM(J8:J19) | ... O20: =SUM(O8:O19)
B24: Dif: | G24: =SUM(C20:E20) | H24: =G24-J5

Sheet SULAMERICA
A1: INTERNAÇÕES HOSPITALARES - ESTUDO CUSTO/RECEITA POR CONVÊNIO - ANO 2024
A3: SULAMERICA
D5: INTERNAÇÕES - | G5: ='[3]intern. diaria convenio'!$O$36 | H5: DIÁRIAS - | J5: ='[3]intern. diaria convenio'!$O$82
A6: CONVÊNIO | C6: DIÁRIAS COBRADAS | G6: MAT/MED | I6: DIÁRIAS | K6: TAXAS | M6: TOTAL
C7: PRIV. | D7: SEMI-P | E7: UTI | F7: UCTI | G7: T. CUSTO | H7: T. VENDA | I7: T. CUSTO | J7: T. VENDA | K7: T. CUSTO | L7: T. VENDA | M7: T. CUSTO | N7: T. VENDA | O7: RESULTADO
A8: JANEIRO | C8: =Total!B28 | D8: =Total!C28 | E8: =Total!D28 | F8: =Total!E28 | G8: =Total!F28 | H8: =Total!G28 | I8: =Total!H28 | J8: =Total!I28 | ... O8: =Total!N28
A9: FEVEREIRO | C9: =Total!B59 | D9: =Total!C59 | E9: =Total!D59 | F9: =Total!E59 | G9: =Total!F59 | H9: =Total!G59 | I9: =Total!H59 | J9: =Total!I59 | ... O9: =Total!N59
A10: MARÇO | C10: =Total!B90 | D10: =Total!C90 | E10: =Total!D90 | F10: =Total!E90 | G10: =Total!F90 | H10: =Total!G90 | I10: =Total!H90 | J10: =Total!I90 | ... O10: =Total!N90
A11: ABRIL | C11: =Total!B121 | D11: =Total!C121 | E11: =Total!D121 | F11: =Total!E121 | G11: =Total!F121 | H11: =Total!G121 | I11: =Total!H121 | J11: =Total!I121 | ... O11: =Total!N121
A12: MAIO | C12: =Total!B152 | D12: =Total!C152 | E12: =Total!D152 | F12: =Total!E152 | G12: =Total!F152 | H12: =Total!G152 | I12: =Total!H152 | J12: =Total!I152 | ... O12: =Total!N152
A13: JUNHO | C13: =Total!B183 | D13: =Total!C183 | E13: =Total!D183 | F13: =Total!E183 | G13: =Total!F183 | H13: =Total!G183 | I13: =Total!H183 | J13: =Total!I183 | ... O13: =Total!N183
A14: JULHO | C14: =Total!B214 | D14: =Total!C214 | E14: =Total!D214 | F14: =Total!E214 | G14: =Total!F214 | H14: =Total!G214 | I14: =Total!H214 | J14: =Total!I214 | ... O14: =Total!N214
A15: AGOSTO | C15: =Total!B245 | D15: =Total!C245 | E15: =Total!D245 | F15: =Total!E245 | G15: =Total!F245 | H15: =Total!G245 | I15: =Total!H245 | J15: =Total!I245 | ... O15: =Total!N245
A16: SETEMBRO | C16: =Total!B276 | D16: =Total!C276 | E16: =Total!D276 | F16: =Total!E276 | G16: =Total!F276 | H16: =Total!G276 | I16: =Total!H276 | J16: =Total!I276 | ... O16: =Total!N276
A17: OUTUBRO | C17: =Total!B307 | D17: =Total!C307 | E17: =Total!D307 | F17: =Total!E307 | G17: =Total!F307 | H17: =Total!G307 | I17: =Total!H307 | J17: =Total!I307 | ... O17: =Total!N307
A18: NOVEMBRO | C18: =Total!B338 | D18: =Total!C338 | E18: =Total!D338 | F18: =Total!E338 | G18: =Total!F338 | H18: =Total!G338 | I18: =Total!H338 | J18: =Total!I338 | ... O18: =Total!N338
A19: DEZEMBRO | C19: =Total!B369 | D19: =Total!C369 | E19: =Total!D369 | F19: =Total!E369 | G19: =Total!F369 | H19: =Total!G369 | I19: =Total!H369 | J19: =Total!I369 | ... O19: =Total!N369
A20: Total | C20: =SUM(C8:C19) | D20: =SUM(D8:D19) | E20: =SUM(E8:E19) | F20: =SUM(F8:F19) | G20: =SUM(G8:G19) | H20: =SUM(H8:H19) | I20: =SUM(I8:I19) | J20: =SUM(J8:J19) | ... O20: =SUM(O8:O19)
B24: Dif: | G24: =SUM(C20:E20) | H24: =G24-J5

Sheet SUS
A1: INTERNAÇÕES HOSPITALARES - ESTUDO CUSTO/RECEITA POR CONVÊNIO - ANO 2024
A3: SUS
D5: INTERNAÇÕES - | G5: ='[3]intern. diaria convenio'!$O$37 | H5: DIÁRIAS - | J5: ='[3]intern. diaria convenio'!$O$83
A6: CONVÊNIO | C6: DIÁRIAS COBRADAS | G6: MAT/MED | I6: DIÁRIAS | K6: TAXAS | M6: TOTAL
C7: PRIV. | D7: ENF | E7: UTI | F7: UCTI | G7: T. CUSTO | H7: T. VENDA | I7: T. CUSTO | J7: T. VENDA | K7: T. CUSTO | L7: T. VENDA | M7: T. CUSTO | N7: T. VENDA | O7: RESULTADO
A8: JANEIRO | C8: =Total!B29 | D8: =Total!C29 | E8: =Total!D29 | F8: =Total!E29 | G8: =Total!F29 | H8: =Total!G29 | I8: =Total!H29 | J8: =Total!I29 | ... O8: =Total!N29
A9: FEVEREIRO | C9: =Total!B60 | D9: =Total!C60 | E9: =Total!D60 | F9: =Total!E60 | G9: =Total!F60 | H9: =Total!G60 | I9: =Total!H60 | J9: =Total!I60 | ... O9: =Total!N60
A10: MARÇO | C10: =Total!B91 | D10: =Total!C91 | E10: =Total!D91 | F10: =Total!E91 | G10: =Total!F91 | H10: =Total!G91 | I10: =Total!H91 | J10: =Total!I91 | ... O10: =Total!N91
A11: ABRIL | C11: =Total!B122 | D11: =Total!C122 | E11: =Total!D122 | F11: =Total!E122 | G11: =Total!F122 | H11: =Total!G122 | I11: =Total!H122 | J11: =Total!I122 | ... O11: =Total!N122
A12: MAIO | C12: =Total!B153 | D12: =Total!C153 | E12: =Total!D153 | F12: =Total!E153 | G12: =Total!F153 | H12: =Total!G153 | I12: =Total!H153 | J12: =Total!I153 | ... O12: =Total!N153
A13: JUNHO | C13: =Total!B184 | D13: =Total!C184 | E13: =Total!D184 | F13: =Total!E184 | G13: =Total!F184 | H13: =Total!G184 | I13: =Total!H184 | J13: =Total!I184 | ... O13: =Total!N184
A14: JULHO | C14: =Total!B215 | D14: =Total!C215 | E14: =Total!D215 | F14: =Total!E215 | G14: =Total!F215 | H14: =Total!G215 | I14: =Total!H215 | J14: =Total!I215 | ... O14: =Total!N215
A15: AGOSTO | C15: =Total!B246 | D15: =Total!C246 | E15: =Total!D246 | F15: =Total!E246 | G15: =Total!F246 | H15: =Total!G246 | I15: =Total!H246 | J15: =Total!I246 | ... O15: =Total!N246
A16: SETEMBRO | C16: =Total!B277 | D16: =Total!C277 | E16: =Total!D277 | F16: =Total!E277 | G16: =Total!F277 | H16: =Total!G277 | I16: =Total!H277 | J16: =Total!I277 | ... O16: =Total!N277
A17: OUTUBRO | C17: =Total!B308 | D17: =Total!C308 | E17: =Total!D308 | F17: =Total!E308 | G17: =Total!F308 | H17: =Total!G308 | I17: =Total!H308 | J17: =Total!I308 | ... O17: =Total!N308
A18: NOVEMBRO | C18: =Total!B339 | D18: =Total!C339 | E18: =Total!D339 | F18: =Total!E339 | G18: =Total!F339 | H18: =Total!G339 | I18: =Total!H339 | J18: =Total!I339 | ... O18: =Total!N339
A19: DEZEMBRO | C19: =Total!B370 | D19: =Total!C370 | E19: =Total!D370 | F19: =Total!E370 | G19: =Total!F370 | H19: =Total!G370 | I19: =Total!H370 | J19: =Total!I370 | ... O19: =Total!N370
A20: Total | C20: =SUM(C8:C19) | D20: =SUM(D8:D19) | E20: =SUM(E8:E19) | F20: =SUM(F8:F19) | G20: =SUM(G8:G19) | H20: =SUM(H8:H19) | I20: =SUM(I8:I19) | J20: =SUM(J8:J19) | ... O20: =SUM(O8:O19)
J23: 14794149

Sheet UNIMED
A1: INTERNAÇÕES HOSPITALARES - ESTUDO CUSTO/RECEITA POR CONVÊNIO - ANO 2024
A3: UNIMED
D5: INTERNAÇÕES - | G5: ='[3]intern. diaria convenio'!$O$41 | H5: DIÁRIAS - | J5: ='[3]intern. diaria convenio'!$O$87
A6: CONVÊNIO | C6: DIÁRIAS COBRADAS | G6: MAT/MED | I6: DIÁRIAS | K6: TAXAS | M6: TOTAL
C7: PRIV. | D7: SEMI-P | E7: UTI | F7: UCTI | G7: T. CUSTO | H7: T. VENDA | I7: T. CUSTO | J7: T. VENDA | K7: T. CUSTO | L7: T. VENDA | M7: T. CUSTO | N7: T. VENDA | O7: RESULTADO | U7: ACORDO
A8: JANEIRO | C8: =Total!B31 | D8: =Total!C31 | E8: =Total!D31 | F8: =Total!E31 | G8: =Total!F31 | H8: =Total!G31 | I8: =Total!H31 | J8: =Total!I31 | ... O8: =Total!N31 | U8: C.M.I
A9: FEVEREIRO | C9: =Total!B62 | D9: =Total!C62 | E9: =Total!D62 | F9: =Total!E62 | G9: =Total!F62 | H9: =Total!G62 | I9: =Total!H62 | J9: =Total!I62 | ... O9: =Total!N62 | U9: CABERGS
A10: MARÇO | C10: =Total!B93 | D10: =Total!C93 | E10: =Total!D93 | F10: =Total!E93 | G10: =Total!F93 | H10: =Total!G93 | I10: =Total!H93 | J10: =Total!I93 | ... O10: =Total!N93 | U10: CAIXA ECONOMICA
A11: ABRIL | C11: =Total!B124 | D11: =Total!C124 | E11: =Total!D124 | F11: =Total!E124 | G11: =Total!F124 | H11: =Total!G124 | I11: =Total!H124 | J11: =Total!I124 | ... O11: =Total!N124 | U11: CASSI
A12: MAIO | C12: =Total!B155 | D12: =Total!C155 | E12: =Total!D155 | F12: =Total!E155 | G12: =Total!F155 | H12: =Total!G155 | I12: =Total!H155 | J12: =Total!I155 | ... O12: =Total!N155 | U12: EMBAIXADOR
A13: JUNHO | C13: =Total!B186 | D13: =Total!C186 | E13: =Total!D186 | F13: =Total!E186 | G13: =Total!F186 | H13: =Total!G186 | I13: =Total!H186 | J13: =Total!I186 | ... O13: =Total!N186 | U13: GEAP
A14: JULHO | C14: =Total!B217 | D14: =Total!C217 | E14: =Total!D217 | F14: =Total!E217 | G14: =Total!F217 | H14: =Total!G217 | I14: =Total!H217 | J14: =Total!I217 | ... O14: =Total!N217 | U14: IPE
A15: AGOSTO | C15: =Total!B248 | D15: =Total!C248 | E15: =Total!D248 | F15: =Total!E248 | G15: =Total!F248 | H15: =Total!G248 | I15: =Total!H248 | J15: =Total!I248 | ... O15: =Total!N248 | U15: IPE SEM PIN PAD
A16: SETEMBRO | C16: =Total!B279 | D16: =Total!C279 | E16: =Total!D279 | F16: =Total!E279 | G16: =Total!F279 | H16: =Total!G279 | I16: =Total!H279 | J16: =Total!I279 | ... O16: =Total!N279 | U16: PARTICULAR
A17: OUTUBRO | C17: =Total!B310 | D17: =Total!C310 | E17: =Total!D310 | F17: =Total!E310 | G17: =Total!F310 | H17: =Total!G310 | I17: =Total!H310 | J17: =Total!I310 | ... O17: =Total!N310 | U17: SAUDE BRADESCO
A18: NOVEMBRO | C18: =Total!B341 | D18: =Total!C341 | E18: =Total!D341 | F18: =Total!E341 | G18: =Total!F341 | H18: =Total!G341 | I18: =Total!H341 | J18: =Total!I341 | ... O18: =Total!N341 | U18: SAUDE MAIOR
A19: DEZEMBRO | C19: =Total!B372 | D19: =Total!C372 | E19: =Total!D372 | F19: =Total!E372 | G19: =Total!F372 | H19: =Total!G372 | I19: =Total!H372 | J19: =Total!I372 | ... O19: =Total!N372 | U19: SOCIOS
A20: Total | C20: =SUM(C8:C19) | D20: =SUM(D8:D19) | E20: =SUM(E8:E19) | F20: =SUM(F8:F19) | G20: =SUM(G8:G19) | H20: =SUM(H8:H19) | I20: =SUM(I8:I19) | J20: =SUM(J8:J19) | ... O20: =SUM(O8:O19) | U20: SULAMERICA
U21: SUS
U22: UNIMED
B24: Dif: | G24: =SUM(C20:E20) | H24: =G24-J5

Sheet E.B.C.T.
A1: INTERNAÇÕES HOSPITALARES - ESTUDO CUSTO/RECEITA POR CONVÊNIO - ANO 2024
A3: E.B.C.T. / POSTAL SAÚDE
D4: INTERNAÇÕES - | G4: ='[3]intern. diaria convenio'!$O$37 | H4: DIÁRIAS - | J4: ='[7]intern. diaria convenio'!$O$82
A5: CONVÊNIO | C5: DIÁRIAS COBRADAS | G5: MAT/MED | I5: DIÁRIAS | K5: TAXAS | M5: TOTAL
C6: PRIV. | D6: SEMI-P | E6: UTI | F6: UCTI | G6: T. CUSTO | H6: T. VENDA | I6: T. CUSTO | J6: T. VENDA | K6: T. CUSTO | L6: T. VENDA | M6: T. CUSTO | N6: T. VENDA | O6: RESULTADO
A7: JANEIRO | C7: =Total!B15 | D7: =Total!C15 | E7: =Total!D15 | F7: =Total!E15 | G7: =Total!F15 | H7: =Total!G15 | I7: =Total!H15 | J7: =Total!I15 | ... O7: =Total!N15
A8: FEVEREIRO | C8: =Total!B45 | D8: =Total!C45 | E8: =Total!D45 | F8: =Total!E45 | G8: =Total!F45 | H8: =Total!G45 | I8: =Total!H45 | J8: =Total!I45 | ... O8: =Total!N45
A9: MARÇO | C9: =Total!B76 | D9: =Total!C76 | E9: =Total!D76 | F9: =Total!E76 | G9: =Total!F76 | H9: =Total!G76 | I9: =Total!H76 | J9: =Total!I76 | ... O9: =Total!N76
A10: ABRIL | C10: =Total!B107 | D10: =Total!C107 | E10: =Total!D107 | F10: =Total!E107 | G10: =Total!F107 | H10: =Total!G107 | I10: =Total!H107 | J10: =Total!I107 | ... O10: =Total!N107
A11: MAIO | C11: =Total!B138 | D11: =Total!C138 | E11: =Total!D138 | F11: =Total!E138 | G11: =Total!F138 | H11: =Total!G138 | I11: =Total!H138 | J11: =Total!I138 | ... O11: =Total!N138
A12: JUNHO | C12: =Total!B169 | D12: =Total!C169 | E12: =Total!D169 | F12: =Total!E169 | G12: =Total!F169 | H12: =Total!G169 | I12: =Total!H169 | J12: =Total!I169 | ... O12: =Total!N169
A13: JULHO | C13: =Total!B200 | D13: =Total!C200 | E13: =Total!D200 | F13: =Total!E200 | G13: =Total!F200 | H13: =Total!G200 | I13: =Total!H200 | J13: =Total!I200 | ... O13: =Total!N200
A14: AGOSTO | C14: =Total!B231 | D14: =Total!C231 | E14: =Total!D231 | F14: =Total!E231 | G14: =Total!F231 | H14: =Total!G231 | I14: =Total!H231 | J14: =Total!I231 | ... O14: =Total!N231
A15: SETEMBRO | C15: =Total!B262 | D15: =Total!C262 | E15: =Total!D262 | F15: =Total!E262 | G15: =Total!F262 | H15: =Total!G262 | I15: =Total!H262 | J15: =Total!I262 | ... O15: =Total!N262
A16: OUTUBRO | C16: =Total!B293 | D16: =Total!C293 | E16: =Total!D293 | F16: =Total!E293 | G16: =Total!F293 | H16: =Total!G293 | I16: =Total!H293 | J16: =Total!I293 | ... O16: =Total!N293
A17: NOVEMBRO | C17: =Total!B324 | D17: =Total!C324 | E17: =Total!D324 | F17: =Total!E324 | G17: =Total!F324 | H17: =Total!G324 | I17: =Total!H324 | J17: =Total!I324 | ... O17: =Total!N324
A18: DEZEMBRO | C18: =Total!B355 | D18: =Total!C355 | E18: =Total!D355 | F18: =Total!E355 | G18: =Total!F355 | H18: =Total!G355 | I18: =Total!H355 | J18: =Total!I355 | ... O18: =Total!N355
A19: Total | C19: =SUM(C7:C18) | D19: =SUM(D7:D18) | E19: =SUM(E7:E18) | F19: =SUM(F7:F18) | G19: =SUM(G7:G18) | H19: =SUM(H7:H18) | I19: =SUM(I7:I18) | J19: =SUM(J7:J18) | ... O19: =SUM(O7:O18)
B23: Dif: | G23: =SUM(C19:E19) | H23: =G23-J4

Sheet Total Acordo Amb-Int
A1: INTERNAÇÕES HOSPITALARES - ESTUDO CUSTO/RECEITA POR CONVÊNIO - ANO 2023
A3: ACORDO TOTAL AMBULATORIO / INTERNADO
D5: INTERNAÇÕES - | G5: =Acordo!G5 | H5: DIÁRIAS - | J5: =Acordo!J5
A6: CONVÊNIO | C6: DIÁRIAS COBRADAS | G6: MAT/MED | I6: DIÁRIAS | K6: TAXAS | M6: TOTAL
C7: PRIV. | D7: SEMI-P | E7: UTI | F7: UCTI | G7: T. CUSTO | H7: T. VENDA | I7: T. CUSTO | J7: T. VENDA | K7: T. CUSTO | L7: T. VENDA | M7: T. CUSTO | N7: T. VENDA | O7: RESULTADO
A8: JANEIRO | C8: =Acordo!C8 | D8: =Acordo!D8 | E8: =Acordo!E8 | F8: =Acordo!F8 | G8: =Acordo!G8+[8]ACORDO!C8 | H8: 0 | I8: =Acordo!I8 | J8: 0 | K8: =Acordo!K8+[8]ACORDO!E8 | L8: 0 | M8: =G8+I8+K8 | N8: =Acordo!N8+[8]ACORDO!$H$8 | O8: =N8-M8
A9: FEVEREIRO | C9: =Acordo!C9 | D9: =Acordo!D9 | E9: =Acordo!E9 | F9: =Acordo!F9 | G9: =Acordo!G9+[8]ACORDO!C9 | H9: 0 | I9: =Acordo!I9 | J9: 0 | K9: =Acordo!K9+[8]ACORDO!E9 | L9: 0 | M9: =G9+I9+K9 | N9: =Acordo!N9+[8]ACORDO!$H$8 | O9: =N9-M9
A10: MARÇO | C10: =Acordo!C10 | D10: =Acordo!D10 | E10: =Acordo!E10 | F10: =Acordo!F10 | G10: =Acordo!G10+[8]ACORDO!C10 | H10: 0 | I10: =Acordo!I10 | J10: 0 | K10: =Acordo!K10+[8]ACORDO!E10 | L10: 0 | M10: =G10+I10+K10 | N10: =Acordo!N10+[8]ACORDO!$H$8 | O10: =N10-M10
A11: ABRIL | C11: =Acordo!C11 | D11: =Acordo!D11 | E11: =Acordo!E11 | F11: =Acordo!F11 | G11: =Acordo!G11+[8]ACORDO!C11 | H11: 0 | I11: =Acordo!I11 | J11: 0 | K11: =Acordo!K11+[8]ACORDO!E11 | L11: 0 | M11: =G11+I11+K11 | N11: =Acordo!N11+[8]ACORDO!$H$8 | O11: =N11-M11
A12: MAIO | C12: =Acordo!C12 | D12: =Acordo!D12 | E12: =Acordo!E12 | F12: =Acordo!F12 | G12: =Acordo!G12+[8]ACORDO!C12 | H12: 0 | I12: =Acordo!I12 | J12: 0 | K12: =Acordo!K12+[8]ACORDO!E12 | L12: 0 | M12: =G12+I12+K12 | N12: =Acordo!N12+[8]ACORDO!$H$8 | O12: =N12-M12
A13: JUNHO | C13: =Acordo!C13 | D13: =Acordo!D13 | E13: =Acordo!E13 | F13: =Acordo!F13 | G13: =Acordo!G13+[8]ACORDO!C13 | H13: 0 | I13: =Acordo!I13 | J13: 0 | K13: =Acordo!K13+[8]ACORDO!E13 | L13: 0 | M13: =G13+I13+K13 | N13: =Acordo!N13+[8]ACORDO!$H$8 | O13: =N13-M13
A14: JULHO | C14: =Acordo!C14 | D14: =Acordo!D14 | E14: =Acordo!E14 | F14: =Acordo!F14 | G14: =Acordo!G14+[8]ACORDO!C14 | H14: 0 | I14: =Acordo!I14 | J14: 0 | K14: =Acordo!K14+[8]ACORDO!E14 | L14: 0 | M14: =G14+I14+K14 | N14: =Acordo!N14+[8]ACORDO!$H$8 | O14: =N14-M14
A15: AGOSTO | C15: =Acordo!C15 | D15: =Acordo!D15 | E15: =Acordo!E15 | F15: =Acordo!F15 | G15: =Acordo!G15+[8]ACORDO!C15 | H15: 0 | I15: =Acordo!I15 | J15: 0 | K15: =Acordo!K15+[8]ACORDO!E15 | L15: 0 | M15: =G15+I15+K15 | N15: =Acordo!N15+[8]ACORDO!$H$8 | O15: =N15-M15
A16: SETEMBRO | C16: =Acordo!C16 | D16: =Acordo!D16 | E16: =Acordo!E16 | F16: =Acordo!F16 | G16: =Acordo!G16+[8]ACORDO!C16 | H16: 0 | I16: =Acordo!I16 | J16: 0 | K16: =Acordo!K16+[8]ACORDO!E16 | L16: 0 | M16: =G16+I16+K16 | N16: =Acordo!N16+[8]ACORDO!$H$8 | O16: =N16-M16
A17: OUTUBRO | C17: =Acordo!C17 | D17: =Acordo!D17 | E17: =Acordo!E17 | F17: =Acordo!F17 | G17: =Acordo!G17+[8]ACORDO!C17 | H17: 0 | I17: =Acordo!I17 | J17: 0 | K17: =Acordo!K17+[8]ACORDO!E17 | L17: 0 | M17: =G17+I17+K17 | N17: =Acordo!N17+[8]ACORDO!$H$8 | O17: =N17-M17
A18: NOVEMBRO | C18: =Acordo!C18 | D18: =Acordo!D18 | E18: =Acordo!E18 | F18: =Acordo!F18 | G18: =Acordo!G18+[8]ACORDO!C18 | H18: 0 | I18: =Acordo!I18 | J18: 0 | K18: =Acordo!K18+[8]ACORDO!E18 | L18: 0 | M18: =G18+I18+K18 | N18: =Acordo!N18+[8]ACORDO!$H$8 | O18: =N18-M18
A19: DEZEMBRO | C19: =Acordo!C19 | D19: =Acordo!D19 | E19: =Acordo!E19 | F19: =Acordo!F19 | G19: =Acordo!G19+[8]ACORDO!C19 | H19: 0 | I19: =Acordo!I19 | J19: 0 | K19: =Acordo!K19+[8]ACORDO!E19 | L19: 0 | M19: =G19+I19+K19 | N19: =Acordo!N19+[8]ACORDO!$H$8 | O19: =N19-M19
A20: Total | C20: 0 | D20: 0 | E20: 0 | F20: 0 | G20: =SUM(G8:G19) | H20: =SUM(H8:H19) | I20: =SUM(I8:I19) | J20: =SUM(J8:J19) | K20: =SUM(K8:K19) | L20: 0 | M20: 733050.63 | N20: =SUM(N8:N19) | O20: =SUM(O8:O19)

Sheet Total C.M.I Amb-Int
A1: INTERNAÇÕES HOSPITALARES - ESTUDO CUSTO/RECEITA POR CONVÊNIO - ANO 2023
A3: C.M.I Internado + Ambulatorial
D5: INTERNAÇÕES - | G5: ='[7]intern. diaria convenio'!$O$8 | H5: DIÁRIAS - | J5: ='[7]intern. diaria convenio'!$O$53
A6: CONVÊNIO | C6: DIÁRIAS COBRADAS | G6: MAT/MED | I6: DIÁRIAS | K6: TAXAS | M6: TOTAL
C7: PRIV. | D7: SEMI-P | E7: UTI | F7: UCTI | G7: T. CUSTO | H7: T. VENDA | I7: T. CUSTO | J7: T. VENDA | K7: T. CUSTO | L7: T. VENDA | M7: T. CUSTO | N7: T. VENDA | O7: RESULTADO
A8: JANEIRO | C8: =Total!B9 | D8: =Total!C9 | E8: =Total!D9 | F8: =Total!E9 | G8: ='C.M.I'!G8+[8]CMI!C8 | H8: ='C.M.I'!H8+[9]CMI!D7 | I8: ='C.M.I'!I8 | J8: =Total!I9 | K8: ='C.M.I'!K8+[8]CMI!G8 | L8: =Total!K9 | M8: =G8+I8+K8 | N8: ='C.M.I'!N8+[10]CMI!H8 | O8: =N8-M8
A9: FEVEREIRO | C9: =Total!B40 | D9: =Total!C40 | E9: =Total!D40 | F9: =Total!E40 | G9: ='C.M.I'!G9+[8]CMI!C9 | H9: ='C.M.I'!H9+[9]CMI!D8 | I9: ='C.M.I'!I9 | J9: =Total!I40 | K9: ='C.M.I'!K9+[8]CMI!G9 | L9: =Total!K40 | M9: =G9+I9+K9 | N9: ='C.M.I'!N9+[8]CMI!H9 | O9: =N9-M9
A10: MARÇO | C10: =Total!B71 | D10: =Total!C71 | E10: =Total!D71 | F10: =Total!E71 | G10: ='C.M.I'!G10+[8]CMI!C10 | H10: ='C.M.I'!H10+[9]CMI!D9 | I10: ='C.M.I'!I10 | J10: =Total!I71 | K10: ='C.M.I'!K10+[8]CMI!G10 | L10: =Total!K71 | M10: =G10+I10+K10 | N10: ='C.M.I'!N10+[8]CMI!H10 | O10: =N10-M10
A11: ABRIL | C11: =Total!B102 | D11: =Total!C102 | E11: =Total!D102 | F11: =Total!E102 | G11: ='C.M.I'!G11+[8]CMI!C11 | H11: ='C.M.I'!H11+[9]CMI!D10 | I11: ='C.M.I'!I11 | J11: =Total!I102 | K11: ='C.M.I'!K11+[8]CMI!G11 | L11: =Total!K102 | M11: =G11+I11+K11 | N11: ='C.M.I'!N11+[8]CMI!H11 | O11: =N11-M11
A12: MAIO | C12: =Total!B133 | D12: =Total!C133 | E12: =Total!D133 | F12: =Total!E133 | G12: ='C.M.I'!G12+[8]CMI!C12 | H12: ='C.M.I'!H12+[9]CMI!D11 | I12: ='C.M.I'!I12 | J12: =Total!I133 | K12: ='C.M.I'!K12+[8]CMI!G12 | L12: =Total!K133 | M12: =G12+I12+K12 | N12: ='C.M.I'!N12+[8]CMI!H12 | O12: =N12-M12
A13: JUNHO | C13: =Total!B164 | D13: =Total!C164 | E13: =Total!D164 | F13: =Total!E164 | G13: ='C.M.I'!G13+[8]CMI!C13 | H13: ='C.M.I'!H13+[9]CMI!D12 | I13: ='C.M.I'!I13 | J13: =Total!I164 | K13: ='C.M.I'!K13+[8]CMI!G13 | L13: =Total!K164 | M13: =G13+I13+K13 | N13: ='C.M.I'!N13+[8]CMI!H13 | O13: =N13-M13
A14: JULHO | C14: =Total!B195 | D14: =Total!C195 | E14: =Total!D195 | F14: =Total!E195 | G14: ='C.M.I'!G14+[8]CMI!C14 | H14: ='C.M.I'!H14+[9]CMI!D13 | I14: ='C.M.I'!I14 | J14: =Total!I195 | K14: ='C.M.I'!K14+[8]CMI!G14 | L14: =Total!K195 | M14: =G14+I14+K14 | N14: ='C.M.I'!N14+[8]CMI!H14 | O14: =N14-M14
A15: AGOSTO | C15: =Total!B226 | D15: =Total!C226 | E15: =Total!D226 | F15: =Total!E226 | G15: ='C.M.I'!G15+[8]CMI!C15 | H15: ='C.M.I'!H15+[9]CMI!D14 | I15: ='C.M.I'!I15 | J15: =Total!I226 | K15: ='C.M.I'!K15+[8]CMI!G15 | L15: =Total!K226 | M15: =G15+I15+K15 | N15: ='C.M.I'!N15+[8]CMI!H15 | O15: =N15-M15
A16: SETEMBRO | C16: =Total!B257 | D16: =Total!C257 | E16: =Total!D257 | F16: =Total!E257 | G16: ='C.M.I'!G16+[8]CMI!C16 | H16: ='C.M.I'!H16+[9]CMI!D15 | I16: ='C.M.I'!I16 | J16: =Total!I257 | K16: ='C.M.I'!K16+[8]CMI!G16 | L16: =Total!K257 | M16: =G16+I16+K16 | N16: ='C.M.I'!N16+[8]CMI!H16 | O16: =N16-M16
A17: OUTUBRO | C17: =Total!B288 | D17: =Total!C288 | E17: =Total!D288 | F17: =Total!E288 | G17: ='C.M.I'!G17+[8]CMI!C17 | H17: ='C.M.I'!H17+[9]CMI!D16 | I17: ='C.M.I'!I17 | J17: =Total!I288 | K17: ='C.M.I'!K17+[8]CMI!G17 | L17: =Total!K288 | M17: =G17+I17+K17 | N17: ='C.M.I'!N17+[8]CMI!H17 | O17: =N17-M17
A18: NOVEMBRO | C18: =Total!B319 | D18: =Total!C319 | E18: =Total!D319 | F18: =Total!E319 | G18: ='C.M.I'!G18+[8]CMI!C18 | H18: ='C.M.I'!H18+[9]CMI!D17 | I18: ='C.M.I'!I18 | J18: =Total!I319 | K18: ='C.M.I'!K18+[8]CMI!G18 | L18: =Total!K319 | M18: =G18+I18+K18 | N18: ='C.M.I'!N18+[8]CMI!H18 | O18: =N18-M18
A19: DEZEMBRO | C19: =Total!B350 | D19: =Total!C350 | E19: =Total!D350 | F19: =Total!E350 | G19: ='C.M.I'!G19+[8]CMI!C19 | H19: ='C.M.I'!H19+[9]CMI!D18 | I19: ='C.M.I'!I19 | J19: =Total!I350 | K19: ='C.M.I'!K19+[8]CMI!G19 | L19: =Total!K350 | M19: =G19+I19+K19 | N19: ='C.M.I'!N19+[8]CMI!H19 | O19: =N19-M19
A20: Total | C20: =SUM(C8:C19) | D20: =SUM(D8:D19) | E20: =SUM(E8:E19) | F20: =SUM(F8:F19) | G20: =SUM(G8:G19) | H20: =SUM(H8:H19) | I20: =SUM(I8:I19) | J20: =SUM(J8:J19) | ... O20: =SUM(O8:O19)

Sheet Total Socios Amb-Int
A1: INTERNAÇÕES HOSPITALARES - ESTUDO CUSTO/RECEITA POR CONVÊNIO - ANO 2023
A3: SOCIOS Ambulatório + Internação
D5: INTERNAÇÕES - | G5: =SOCIOS!G5 | H5: DIÁRIAS - | J5: =SOCIOS!J5
A6: CONVÊNIO | C6: DIÁRIAS COBRADAS | G6: MAT/MED | I6: DIÁRIAS | K6: TAXAS | M6: TOTAL
C7: PRIV. | D7: SEMI-P | E7: UTI | F7: UCTI | G7: T. CUSTO | H7: T. VENDA | I7: T. CUSTO | J7: T. VENDA | K7: T. CUSTO | L7: T. VENDA | M7: T. CUSTO | N7: T. VENDA | O7: RESULTADO
A8: JANEIRO | C8: =SOCIOS!C8 | D8: =SOCIOS!D8 | E8: =SOCIOS!E8 | F8: =SOCIOS!F8 | G8: =SOCIOS!G8+[8]SÓCIOS!$C$8 | H8: =SOCIOS!H8+[9]SÓCIOS!D7 | I8: =SOCIOS!I8 | J8: =Total!I28 | K8: =SOCIOS!K8+[8]SÓCIOS!$E$8 | L8: =SOCIOS!L8+[9]SÓCIOS!H7 | M8: =G8+I8+K8 | N8: =SOCIOS!N8 | O8: =N8-M8
A9: FEVEREIRO | C9: =SOCIOS!C9 | D9: =SOCIOS!D9 | E9: =SOCIOS!E9 | F9: =SOCIOS!F9 | G9: =SOCIOS!G9+[8]SÓCIOS!$C$8 | H9: =SOCIOS!H9+[9]SÓCIOS!D8 | I9: =SOCIOS!I9 | J9: =Total!I59 | K9: =SOCIOS!K9+[8]SÓCIOS!$E$8 | L9: =SOCIOS!L9+[9]SÓCIOS!H8 | M9: =G9+I9+K9 | N9: =SOCIOS!N9 | O9: =N9-M9
A10: MARÇO | C10: =SOCIOS!C10 | D10: =SOCIOS!D10 | E10: =SOCIOS!E10 | F10: =SOCIOS!F10 | G10: =SOCIOS!G10+[8]SÓCIOS!$C$8 | H10: =SOCIOS!H10+[9]SÓCIOS!D9 | I10: =SOCIOS!I10 | J10: =Total!I90 | K10: =SOCIOS!K10+[8]SÓCIOS!$E$8 | L10: =SOCIOS!L10+[9]SÓCIOS!H9 | M10: =G10+I10+K10 | N10: =SOCIOS!N10 | O10: =N10-M10
A11: ABRIL | C11: =SOCIOS!C11 | D11: =SOCIOS!D11 | E11: =SOCIOS!E11 | F11: =SOCIOS!F11 | G11: =SOCIOS!G11+[8]SÓCIOS!$C$8 | H11: =SOCIOS!H11+[9]SÓCIOS!D10 | I11: =SOCIOS!I11 | J11: =Total!I121 | K11: =SOCIOS!K11+[8]SÓCIOS!$E$8 | L11: =SOCIOS!L11+[9]SÓCIOS!H10 | M11: =G11+I11+K11 | N11: =SOCIOS!N11 | O11: =N11-M11
A12: MAIO | C12: =SOCIOS!C12 | D12: =SOCIOS!D12 | E12: =SOCIOS!E12 | F12: =SOCIOS!F12 | G12: =SOCIOS!G12+[8]SÓCIOS!$C$8 | H12: =SOCIOS!H12+[9]SÓCIOS!D11 | I12: =SOCIOS!I12 | J12: =Total!I152 | K12: =SOCIOS!K12+[8]SÓCIOS!$E$8 | L12: =SOCIOS!L12+[9]SÓCIOS!H11 | M12: =G12+I12+K12 | N12: =SOCIOS!N12 | O12: =N12-M12
A13: JUNHO | C13: =SOCIOS!C13 | D13: =SOCIOS!D13 | E13: =SOCIOS!E13 | F13: =SOCIOS!F13 | G13: =SOCIOS!G13+[8]SÓCIOS!$C$8 | H13: =SOCIOS!H13+[9]SÓCIOS!D12 | I13: =SOCIOS!I13 | J13: =Total!I183 | K13: =SOCIOS!K13+[8]SÓCIOS!$E$8 | L13: =SOCIOS!L13+[9]SÓCIOS!H12 | M13: =G13+I13+K13 | N13: =SOCIOS!N13 | O13: =N13-M13
A14: JULHO | C14: =SOCIOS!C14 | D14: =SOCIOS!D14 | E14: =SOCIOS!E14 | F14: =SOCIOS!F14 | G14: =SOCIOS!G14+[8]SÓCIOS!$C$8 | H14: =SOCIOS!H14+[9]SÓCIOS!D13 | I14: =SOCIOS!I14 | J14: =Total!I214 | K14: =SOCIOS!K14+[8]SÓCIOS!$E$8 | L14: =SOCIOS!L14+[9]SÓCIOS!H13 | M14: =G14+I14+K14 | N14: =SOCIOS!N14 | O14: =N14-M14
A15: AGOSTO | C15: =SOCIOS!C15 | D15: =SOCIOS!D15 | E15: =SOCIOS!E15 | F15: =SOCIOS!F15 | G15: =SOCIOS!G15+[8]SÓCIOS!$C$8 | H15: =SOCIOS!H15+[9]SÓCIOS!D14 | I15: =SOCIOS!I15 | J15: =Total!I245 | K15: =SOCIOS!K15+[8]SÓCIOS!$E$8 | L15: =SOCIOS!L15+[9]SÓCIOS!H14 | M15: =G15+I15+K15 | N15: =SOCIOS!N15 | O15: =N15-M15
A16: SETEMBRO | C16: =SOCIOS!C16 | D16: =SOCIOS!D16 | E16: =SOCIOS!E16 | F16: =SOCIOS!F16 | G16: =SOCIOS!G16+[8]SÓCIOS!$C$8 | H16: =SOCIOS!H16+[9]SÓCIOS!D15 | I16: =SOCIOS!I16 | J16: =Total!I276 | K16: =SOCIOS!K16+[8]SÓCIOS!$E$8 | L16: =SOCIOS!L16+[9]SÓCIOS!H15 | M16: =G16+I16+K16 | N16: =SOCIOS!N16 | O16: =N16-M16
A17: OUTUBRO | C17: =SOCIOS!C17 | D17: =SOCIOS!D17 | E17: =SOCIOS!E17 | F17: =SOCIOS!F17 | G17: =SOCIOS!G17+[8]SÓCIOS!$C$8 | H17: =SOCIOS!H17+[9]SÓCIOS!D16 | I17: =SOCIOS!I17 | J17: =Total!I307 | K17: =SOCIOS!K17+[8]SÓCIOS!$E$8 | L17: =SOCIOS!L17+[9]SÓCIOS!H16 | M17: =G17+I17+K17 | N17: =SOCIOS!N17 | O17: =N17-M17
A18: NOVEMBRO | C18: =SOCIOS!C18 | D18: =SOCIOS!D18 | E18: =SOCIOS!E18 | F18: =SOCIOS!F18 | G18: =SOCIOS!G18+[8]SÓCIOS!$C$8 | H18: =SOCIOS!H18+[9]SÓCIOS!D17 | I18: =SOCIOS!I18 | J18: =Total!I338 | K18: =SOCIOS!K18+[8]SÓCIOS!$E$8 | L18: =SOCIOS!L18+[9]SÓCIOS!H17 | M18: =G18+I18+K18 | N18: =SOCIOS!N18 | O18: =N18-M18
A19: DEZEMBRO | C19: =SOCIOS!C19 | D19: =SOCIOS!D19 | E19: =SOCIOS!E19 | F19: =SOCIOS!F19 | G19: =SOCIOS!G19+[8]SÓCIOS!$C$8 | H19: =SOCIOS!H19+[9]SÓCIOS!D18 | I19: =SOCIOS!I19 | J19: =Total!I369 | K19: =SOCIOS!K19+[8]SÓCIOS!$E$8 | L19: =SOCIOS!L19+[9]SÓCIOS!H18 | M19: =G19+I19+K19 | N19: =SOCIOS!N19 | O19: =N19-M19
A20: Total | C20: =SUM(C8:C19) | D20: =SUM(D8:D19) | E20: =SUM(E8:E19) | F20: =SUM(F8:F19) | G20: =SUM(G8:G19) | H20: =SUM(H8:H19) | I20: =SUM(I8:I19) | J20: =SUM(J8:J19) | ... O20: =SUM(O8:O19)

Sheet Assefaz
A1: INTERNAÇÕES HOSPITALARES - ESTUDO CUSTO/RECEITA POR CONVÊNIO - ANO 2017
A3: ASSEFAZ
D4: INTERNAÇÕES - | G4: ='[11]intern. diaria convenio'!$O$5 | H4: DIÁRIAS - | J4: ='[11]intern. diaria convenio'!$O$50
A5: CONVÊNIO | C5: DIÁRIAS COBRADAS | G5: MAT/MED | I5: DIÁRIAS | K5: TAXAS | M5: TOTAL
C6: PRIV. | D6: SEMI-P | E6: UTI | F6: UCTI | G6: T. CUSTO | H6: T. VENDA | I6: T. CUSTO | J6: T. VENDA | K6: T. CUSTO | L6: T. VENDA | M6: T. CUSTO | N6: T. VENDA | O6: RESULTADO
A7: JANEIRO | C7: =Total!B8 | D7: =Total!C8 | E7: =Total!D8 | F7: =Total!E8 | G7: =Total!F8 | H7: =Total!G8 | I7: =Total!H8 | J7: =Total!I8 | ... O7: =Total!N8
A8: FEVEREIRO | C8: =Total!B39 | D8: =Total!C39 | E8: =Total!D39 | F8: =Total!E39 | G8: =Total!F39 | H8: =Total!G39 | I8: =Total!H39 | J8: =Total!I39 | ... O8: =Total!N39
A9: MARÇO | C9: =Total!B70 | D9: =Total!C70 | E9: =Total!D70 | F9: =Total!E70 | G9: =Total!F70 | H9: =Total!G70 | I9: =Total!H70 | J9: =Total!I70 | ... O9: =Total!N70
A10: ABRIL | C10: =Total!B101 | D10: =Total!C101 | E10: =Total!D101 | F10: =Total!E101 | G10: =Total!F101 | H10: =Total!G101 | I10: =Total!H101 | J10: =Total!I101 | ... O10: =Total!N101
A11: MAIO | C11: =Total!B132 | D11: =Total!C132 | E11: =Total!D132 | F11: =Total!E132 | G11: =Total!F132 | H11: =Total!G132 | I11: =Total!H132 | J11: =Total!I132 | ... O11: =Total!N132
A12: JUNHO | C12: =Total!B163 | D12: =Total!C163 | E12: =Total!D163 | F12: =Total!E163 | G12: =Total!F163 | H12: =Total!G163 | I12: =Total!H163 | J12: =Total!I163 | ... O12: =Total!N163
A13: JULHO | C13: =Total!B194 | D13: =Total!C194 | E13: =Total!D194 | F13: =Total!E194 | G13: =Total!F194 | H13: =Total!G194 | I13: =Total!H194 | J13: =Total!I194 | ... O13: =Total!N194
A14: AGOSTO | C14: =Total!B225 | D14: =Total!C225 | E14: =Total!D225 | F14: =Total!E225 | G14: =Total!F225 | H14: =Total!G225 | I14: =Total!H225 | J14: =Total!I225 | ... O14: =Total!N225
A15: SETEMBRO | C15: =Total!B256 | D15: =Total!C256 | E15: =Total!D256 | F15: =Total!E256 | G15: =Total!F256 | H15: =Total!G256 | I15: =Total!H256 | J15: =Total!I256 | ... O15: =Total!N256
A16: OUTUBRO | C16: =Total!B287 | D16: =Total!C287 | E16: =Total!D287 | F16: =Total!E287 | G16: =Total!F287 | H16: =Total!G287 | I16: =Total!H287 | J16: =Total!I287 | ... O16: =Total!N287
A17: NOVEMBRO | C17: =Total!B318 | D17: =Total!C318 | E17: =Total!D318 | F17: =Total!E318 | G17: =Total!F318 | H17: =Total!G318 | I17: =Total!H318 | J17: =Total!I318 | ... O17: =Total!N318
A18: DEZEMBRO | C18: =Total!B349 | D18: =Total!C349 | E18: =Total!D349 | F18: =Total!E349 | G18: =Total!F349 | H18: =Total!G349 | I18: =Total!H349 | J18: =Total!I349 | ... O18: =Total!N349
A19: Total | C19: =SUM(C7:C18) | D19: =SUM(D7:D18) | E19: =SUM(E7:E18) | F19: =SUM(F7:F18) | G19: =SUM(G7:G18) | H19: =SUM(H7:H18) | I19: =SUM(I7:I18) | J19: =SUM(J7:J18) | ... O19: =SUM(O7:O18)
B23: Dif: | G23: =SUM(C19:E19) | H23: =G23-J4

Sheet CAPESAUDE
A1: INTERNAÇÕES HOSPITALARES - ESTUDO CUSTO/RECEITA POR CONVÊNIO - ANO 2018
A3: CAPESAUDE
D4: INTERNAÇÕES - | G4: ='[12]intern. diaria convenio'!$O$10 | H4: DIÁRIAS - | J4: ='[12]intern. diaria convenio'!$O$55
A5: CONVÊNIO | C5: DIÁRIAS COBRADAS | G5: MAT/MED | I5: DIÁRIAS | K5: TAXAS | M5: TOTAL
C6: PRIV. | D6: SEMI-P | E6: UTI | F6: UCTI | G6: T. CUSTO | H6: T. VENDA | I6: T. CUSTO | J6: T. VENDA | K6: T. CUSTO | L6: T. VENDA | M6: T. CUSTO | N6: T. VENDA | O6: RESULTADO
A7: JANEIRO | C7: =Total!B11 | D7: =Total!C11 | E7: =Total!D11 | F7: =Total!E11 | G7: =Total!F11 | H7: =Total!G11 | I7: =Total!H11 | J7: =Total!I11 | ... O7: =Total!N11
A8: FEVEREIRO | C8: =Total!B42 | D8: =Total!C42 | E8: =Total!D42 | F8: =Total!E42 | G8: =Total!F42 | H8: =Total!G42 | I8: =Total!H42 | J8: =Total!I42 | ... O8: =Total!N42
A9: MARÇO | C9: =Total!B73 | D9: =Total!C73 | E9: =Total!D73 | F9: =Total!E73 | G9: =Total!F73 | H9: =Total!G73 | I9: =Total!H73 | J9: =Total!I73 | ... O9: =Total!N73
A10: ABRIL | C10: =Total!B104 | D10: =Total!C104 | E10: =Total!D104 | F10: =Total!E104 | G10: =Total!F104 | H10: =Total!G104 | I10: =Total!H104 | J10: =Total!I104 | ... O10: =Total!N104
A11: MAIO | C11: =Total!B135 | D11: =Total!C135 | E11: =Total!D135 | F11: =Total!E135 | G11: =Total!F135 | H11: =Total!G135 | I11: =Total!H135 | J11: =Total!I135 | ... O11: =Total!N135
A12: JUNHO | C12: =Total!B166 | D12: =Total!C166 | E12: =Total!D166 | F12: =Total!E166 | G12: =Total!F166 | H12: =Total!G166 | I12: =Total!H166 | J12: =Total!I166 | ... O12: =Total!N166
A13: JULHO | C13: =Total!B197 | D13: =Total!C197 | E13: =Total!D197 | F13: =Total!E197 | G13: =Total!F197 | H13: =Total!G197 | I13: =Total!H197 | J13: =Total!I197 | ... O13: =Total!N197
A14: AGOSTO | C14: =Total!B228 | D14: =Total!C228 | E14: =Total!D228 | F14: =Total!E228 | G14: =Total!F228 | H14: =Total!G228 | I14: =Total!H228 | J14: =Total!I228 | ... O14: =Total!N228
A15: SETEMBRO | C15: =Total!B259 | D15: =Total!C259 | E15: =Total!D259 | F15: =Total!E259 | G15: =Total!F259 | H15: =Total!G259 | I15: =Total!H259 | J15: =Total!I259 | ... O15: =Total!N259
A16: OUTUBRO | C16: =Total!B290 | D16: =Total!C290 | E16: =Total!D290 | F16: =Total!E290 | G16: =Total!F290 | H16: =Total!G290 | I16: =Total!H290 | J16: =Total!I290 | ... O16: =Total!N290
A17: NOVEMBRO | C17: =Total!B321 | D17: =Total!C321 | E17: =Total!D321 | F17: =Total!E321 | G17: =Total!F321 | H17: =Total!G321 | I17: =Total!H321 | J17: =Total!I321 | ... O17: =Total!N321
A18: DEZEMBRO | C18: =Total!B352 | D18: =Total!C352 | E18: =Total!D352 | F18: =Total!E352 | G18: =Total!F352 | H18: =Total!G352 | I18: =Total!H352 | J18: =Total!I352 | ... O18: =Total!N352
A19: Total | C19: =SUM(C7:C18) | D19: =SUM(D7:D18) | E19: =SUM(E7:E18) | F19: =SUM(F7:F18) | G19: =SUM(G7:G18) | H19: =SUM(H7:H18) | I19: =SUM(I7:I18) | J19: =SUM(J7:J18) | ... O19: =SUM(O7:O18)
B23: Dif: | G23: =SUM(C19:E19) | H23: =G23-J4

Sheet CASEMBRAPA
A1: INTERNAÇÕES HOSPITALARES - ESTUDO CUSTO/RECEITA POR CONVÊNIO - ANO 2018
A3: CASEMBRAPA
D4: INTERNAÇÕES - | G4: ='[12]intern. diaria convenio'!$O$16 | H4: DIÁRIAS - | J4: ='[12]intern. diaria convenio'!$O$61
A5: CONVÊNIO | C5: DIÁRIAS COBRADAS | G5: MAT/MED | I5: DIÁRIAS | K5: TAXAS | M5: TOTAL
C6: PRIV. | D6: SEMI-P | E6: UTI | F6: UCTI | G6: T. CUSTO | H6: T. VENDA | I6: T. CUSTO | J6: T. VENDA | K6: T. CUSTO | L6: T. VENDA | M6: T. CUSTO | N6: T. VENDA | O6: RESULTADO
A7: JANEIRO | C7: =Total!B12 | D7: =Total!C12 | E7: =Total!D12 | F7: =Total!E12 | G7: =Total!F12 | H7: =Total!G12 | I7: =Total!H12 | J7: =Total!I12 | ... O7: =Total!N12
A8: FEVEREIRO | C8: =Total!B43 | D8: =Total!C43 | E8: =Total!D43 | F8: =Total!E43 | G8: =Total!F43 | H8: =Total!G43 | I8: =Total!H43 | J8: =Total!I43 | ... O8: =Total!N43
A9: MARÇO | C9: =Total!B74 | D9: =Total!C74 | E9: =Total!D74 | F9: =Total!E74 | G9: =Total!F74 | H9: =Total!G74 | I9: =Total!H74 | J9: =Total!I74 | ... O9: =Total!N74
A10: ABRIL | C10: =Total!B105 | D10: =Total!C105 | E10: =Total!D105 | F10: =Total!E105 | G10: =Total!F105 | H10: =Total!G105 | I10: =Total!H105 | J10: =Total!I105 | ... O10: =Total!N105
A11: MAIO | C11: =Total!B136 | D11: =Total!C136 | E11: =Total!D136 | F11: =Total!E136 | G11: =Total!F136 | H11: =Total!G136 | I11: =Total!H136 | J11: =Total!I136 | ... O11: =Total!N136
A12: JUNHO | C12: =Total!B167 | D12: =Total!C167 | E12: =Total!D167 | F12: =Total!E167 | G12: =Total!F167 | H12: =Total!G167 | I12: =Total!H167 | J12: =Total!I167 | ... O12: =Total!N167
A13: JULHO | C13: =Total!B198 | D13: =Total!C198 | E13: =Total!D198 | F13: =Total!E198 | G13: =Total!F198 | H13: =Total!G198 | I13: =Total!H198 | J13: =Total!I198 | ... O13: =Total!N198
A14: AGOSTO | C14: =Total!B229 | D14: =Total!C229 | E14: =Total!D229 | F14: =Total!E229 | G14: =Total!F229 | H14: =Total!G229 | I14: =Total!H229 | J14: =Total!I229 | ... O14: =Total!N229
A15: SETEMBRO | C15: =Total!B260 | D15: =Total!C260 | E15: =Total!D260 | F15: =Total!E260 | G15: =Total!F260 | H15: =Total!G260 | I15: =Total!H260 | J15: =Total!I260 | ... O15: =Total!N260
A16: OUTUBRO | C16: =Total!B291 | D16: =Total!C291 | E16: =Total!D291 | F16: =Total!E291 | G16: =Total!F291 | H16: =Total!G291 | I16: =Total!H291 | J16: =Total!I291 | ... O16: =Total!N291
A17: NOVEMBRO | C17: =Total!B322 | D17: =Total!C322 | E17: =Total!D322 | F17: =Total!E322 | G17: =Total!F322 | H17: =Total!G322 | I17: =Total!H322 | J17: =Total!I322 | ... O17: =Total!N322
A18: DEZEMBRO | C18: =Total!B353 | D18: =Total!C353 | E18: =Total!D353 | F18: =Total!E353 | G18: =Total!F353 | H18: =Total!G353 | I18: =Total!H353 | J18: =Total!I353 | ... O18: =Total!N353
A19: Total | C19: =SUM(C7:C18) | D19: =SUM(D7:D18) | E19: =SUM(E7:E18) | F19: =SUM(F7:F18) | G19: =SUM(G7:G18) | H19: =SUM(H7:H18) | I19: =SUM(I7:I18) | J19: =SUM(J7:J18) | ... O19: =SUM(O7:O18)

Sheet FUSEX
A1: INTERNAÇÕES HOSPITALARES - ESTUDO CUSTO/RECEITA POR CONVÊNIO - ANO 2018
A3: FUSEX
D4: INTERNAÇÕES - | G4: ='[12]intern. diaria convenio'!$O$19 | H4: DIÁRIAS - | J4: ='[12]intern. diaria convenio'!$O$64
A5: CONVÊNIO | C5: DIÁRIAS COBRADAS | G5: MAT/MED | I5: DIÁRIAS | K5: TAXAS | M5: TOTAL
C6: PRIV. | D6: SEMI-P | E6: UTI | F6: UCTI | G6: T. CUSTO | H6: T. VENDA | I6: T. CUSTO | J6: T. VENDA | K6: T. CUSTO | L6: T. VENDA | M6: T. CUSTO | N6: T. VENDA | O6: RESULTADO
A7: JANEIRO | C7: =Total!B16 | D7: =Total!C16 | E7: =Total!D16 | F7: =Total!E16 | G7: =Total!F16 | H7: =Total!G16 | I7: =Total!H16 | J7: =Total!I16 | ... O7: =Total!N16
A8: FEVEREIRO | C8: =Total!B47 | D8: =Total!C47 | E8: =Total!D47 | F8: =Total!E47 | G8: =Total!F47 | H8: =Total!G47 | I8: =Total!H47 | J8: =Total!I47 | ... O8: =Total!N47
A9: MARÇO | C9: =Total!B78 | D9: =Total!C78 | E9: =Total!D78 | F9: =Total!E78 | G9: =Total!F78 | H9: =Total!G78 | I9: =Total!H78 | J9: =Total!I78 | ... O9: =Total!N78
A10: ABRIL | C10: =Total!B109 | D10: =Total!C109 | E10: =Total!D109 | F10: =Total!E109 | G10: =Total!F109 | H10: =Total!G109 | I10: =Total!H109 | J10: =Total!I109 | ... O10: =Total!N109
A11: MAIO | C11: =Total!B140 | D11: =Total!C140 | E11: =Total!D140 | F11: =Total!E140 | G11: =Total!F140 | H11: =Total!G140 | I11: =Total!H140 | J11: =Total!I140 | ... O11: =Total!N140
A12: JUNHO | C12: =Total!B171 | D12: =Total!C171 | E12: =Total!D171 | F12: =Total!E171 | G12: =Total!F171 | H12: =Total!G171 | I12: =Total!H171 | J12: =Total!I171 | ... O12: =Total!N171
A13: JULHO | C13: =Total!B202 | D13: =Total!C202 | E13: =Total!D202 | F13: =Total!E202 | G13: =Total!F202 | H13: =Total!G202 | I13: =Total!H202 | J13: =Total!I202 | ... O13: =Total!N202
A14: AGOSTO | C14: =Total!B233 | D14: =Total!C233 | E14: =Total!D233 | F14: =Total!E233 | G14: =Total!F233 | H14: =Total!G233 | I14: =Total!H233 | J14: =Total!I233 | ... O14: =Total!N233
A15: SETEMBRO | C15: =Total!B264 | D15: =Total!C264 | E15: =Total!D264 | F15: =Total!E264 | G15: =Total!F264 | H15: =Total!G264 | I15: =Total!H264 | J15: =Total!I264 | ... O15: =Total!N264
A16: OUTUBRO | C16: =Total!B295 | D16: =Total!C295 | E16: =Total!D295 | F16: =Total!E295 | G16: =Total!F295 | H16: =Total!G295 | I16: =Total!H295 | J16: =Total!I295 | ... O16: =Total!N295
A17: NOVEMBRO | C17: =Total!B326 | D17: =Total!C326 | E17: =Total!D326 | F17: =Total!E326 | G17: =Total!F326 | H17: =Total!G326 | I17: =Total!H326 | J17: =Total!I326 | ... O17: =Total!N326
A18: DEZEMBRO | C18: =Total!B357 | D18: =Total!C357 | E18: =Total!D357 | F18: =Total!E357 | G18: =Total!F357 | H18: =Total!G357 | I18: =Total!H357 | J18: =Total!I357 | ... O18: =Total!N357
A19: Total | C19: =SUM(C7:C18) | D19: =SUM(D7:D18) | E19: =SUM(E7:E18) | F19: =SUM(F7:F18) | G19: =SUM(G7:G18) | H19: =SUM(H7:H18) | I19: =SUM(I7:I18) | J19: =SUM(J7:J18) | ... O19: =SUM(O7:O18)
B23: Dif: | G23: =SUM(C19:E19) | H23: =G23-J4

Sheet SAUDE PAS
A1: INTERNAÇÕES HOSPITALARES - ESTUDO CUSTO/RECEITA POR CONVÊNIO - ANO 2018
A3: SAUDE PAS MEDICINA
D4: INTERNAÇÕES - | G4: ='[12]intern. diaria convenio'!$O$21 | H4: DIÁRIAS - | J4: ='[12]intern. diaria convenio'!$O$66
A5: CONVÊNIO | C5: DIÁRIAS COBRADAS | G5: MAT/MED | I5: DIÁRIAS | K5: TAXAS | M5: TOTAL
C6: PRIV. | D6: SEMI-P | E6: UTI | F6: UCTI | G6: T. CUSTO | H6: T. VENDA | I6: T. CUSTO | J6: T. VENDA | K6: T. CUSTO | L6: T. VENDA | M6: T. CUSTO | N6: T. VENDA | O6: RESULTADO
A7: JANEIRO | C7: =Total!B18 | D7: =Total!C18 | E7: =Total!D18 | F7: =Total!E18 | G7: =Total!F18 | H7: =Total!G18 | I7: =Total!H18 | J7: =Total!I18 | ... O7: =Total!N18
A8: FEVEREIRO | C8: =Total!B49 | D8: =Total!C49 | E8: =Total!D49 | F8: =Total!E49 | G8: =Total!F49 | H8: =Total!G49 | I8: =Total!H49 | J8: =Total!I49 | ... O8: =Total!N49
A9: MARÇO | C9: =Total!B80 | D9: =Total!C80 | E9: =Total!D80 | F9: =Total!E80 | G9: =Total!F80 | H9: =Total!G80 | I9: =Total!H80 | J9: =Total!I80 | ... O9: =Total!N80
A10: ABRIL | C10: =Total!#REF! | D10: =Total!#REF! | E10: =Total!#REF! | F10: =Total!#REF! | G10: =Total!F111 | H10: =Total!G111 | I10: =Total!H111 | J10: =Total!I111 | K10: =Total!J111 | L10: =Total!K111 | M10: =Total!L111 | N10: =Total!M111 | O10: =Total!N111
A11: MAIO | C11: =Total!B142 | D11: =Total!C142 | E11: =Total!D142 | F11: =Total!E142 | G11: =Total!F142 | H11: =Total!G142 | I11: =Total!H142 | J11: =Total!I142 | ... O11: =Total!N142
A12: JUNHO | C12: =Total!B173 | D12: =Total!C173 | E12: =Total!D173 | F12: =Total!E173 | G12: =Total!F173 | H12: =Total!G173 | I12: =Total!H173 | J12: =Total!I173 | ... O12: =Total!N173
A13: JULHO | C13: =Total!B204 | D13: =Total!C204 | E13: =Total!D204 | F13: =Total!E204 | G13: =Total!F204 | H13: =Total!G204 | I13: =Total!H204 | J13: =Total!I204 | ... O13: =Total!N204
A14: AGOSTO | C14: =Total!B235 | D14: =Total!C235 | E14: =Total!D235 | F14: =Total!E235 | G14: =Total!F235 | H14: =Total!G235 | I14: =Total!H235 | J14: =Total!I235 | ... O14: =Total!N235
A15: SETEMBRO | C15: =Total!B266 | D15: =Total!C266 | E15: =Total!D266 | F15: =Total!E266 | G15: =Total!F266 | H15: =Total!G266 | I15: =Total!H266 | J15: =Total!I266 | ... O15: =Total!N266
A16: OUTUBRO | C16: =Total!B297 | D16: =Total!C297 | E16: =Total!D297 | F16: =Total!E297 | G16: =Total!F297 | H16: =Total!G297 | I16: =Total!H297 | J16: =Total!I297 | ... O16: =Total!N297
A17: NOVEMBRO | C17: =Total!B328 | D17: =Total!C328 | E17: =Total!D328 | F17: =Total!E328 | G17: =Total!F328 | H17: =Total!G328 | I17: =Total!H328 | J17: =Total!I328 | ... O17: =Total!N328
A18: DEZEMBRO | C18: =Total!B359 | D18: =Total!C359 | E18: =Total!D359 | F18: =Total!E359 | G18: =Total!F359 | H18: =Total!G359 | I18: =Total!H359 | J18: =Total!I359 | ... O18: =Total!N359
A19: Total | C19: =SUM(C7:C18) | D19: =SUM(D7:D18) | E19: =SUM(E7:E18) | F19: =SUM(F7:F18) | G19: =SUM(G7:G18) | H19: =SUM(H7:H18) | I19: =SUM(I7:I18) | J19: =SUM(J7:J18) | ... O19: =SUM(O7:O18)

Sheet IPIRANGA - SAMEISA
A1: INTERNAÇÕES HOSPITALARES - ESTUDO CUSTO/RECEITA POR CONVÊNIO - ANO 2017
A3: IPIRANGA - SAMEISA
D4: INTERNAÇÕES - | F4: ='[12]intern. diaria convenio'!$O$24 | H4: DIÁRIAS - | J4: ='[12]intern. diaria convenio'!$O$69
A5: CONVÊNIO | C5: DIÁRIAS COBRADAS | G5: MAT/MED | I5: DIÁRIAS | K5: TAXAS | M5: TOTAL
C6: PRIV. | D6: SEMI-P | E6: UTI | F6: UCTI | G6: T. CUSTO | H6: T. VENDA | I6: T. CUSTO | J6: T. VENDA | K6: T. CUSTO | L6: T. VENDA | M6: T. CUSTO | N6: T. VENDA | O6: RESULTADO
A7: JANEIRO | C7: =Total!B21 | D7: =Total!C21 | E7: =Total!D21 | F7: =Total!E21 | G7: =Total!F21 | H7: =Total!G21 | I7: =Total!H21 | J7: =Total!I21 | ... O7: =Total!N21
A8: FEVEREIRO | C8: =Total!B52 | D8: =Total!C52 | E8: =Total!D52 | F8: =Total!E52 | G8: =Total!F52 | H8: =Total!G52 | I8: =Total!H52 | J8: =Total!I52 | ... O8: =Total!N52
A9: MARÇO | C9: =Total!B83 | D9: =Total!C83 | E9: =Total!D83 | F9: =Total!E83 | G9: =Total!F83 | H9: =Total!G83 | I9: =Total!H83 | J9: =Total!I83 | ... O9: =Total!N83
A10: ABRIL | C10: =Total!B114 | D10: =Total!C114 | E10: =Total!D114 | F10: =Total!E114 | G10: =Total!F114 | H10: =Total!G114 | I10: =Total!H114 | J10: =Total!I114 | ... O10: =Total!N114
A11: MAIO | C11: =Total!B145 | D11: =Total!C145 | E11: =Total!D145 | F11: =Total!E145 | G11: =Total!F145 | H11: =Total!G145 | I11: =Total!H145 | J11: =Total!I145 | ... O11: =Total!N145
A12: JUNHO | C12: =Total!B176 | D12: =Total!C176 | E12: =Total!D176 | F12: =Total!E176 | G12: =Total!F176 | H12: =Total!G176 | I12: =Total!H176 | J12: =Total!I176 | ... O12: =Total!N176
A13: JULHO | C13: =Total!B207 | D13: =Total!C207 | E13: =Total!D207 | F13: =Total!E207 | G13: =Total!F207 | H13: =Total!G207 | I13: =Total!H207 | J13: =Total!I207 | ... O13: =Total!N207
A14: AGOSTO | C14: =Total!B238 | D14: =Total!C238 | E14: =Total!D238 | F14: =Total!E238 | G14: =Total!F238 | H14: =Total!G238 | I14: =Total!H238 | J14: =Total!I238 | ... O14: =Total!N238
A15: SETEMBRO | C15: =Total!B269 | D15: =Total!C269 | E15: =Total!D269 | F15: =Total!E269 | G15: =Total!F269 | H15: =Total!G269 | I15: =Total!H269 | J15: =Total!I269 | ... O15: =Total!N269
A16: OUTUBRO | C16: =Total!B300 | D16: =Total!C300 | E16: =Total!D300 | F16: =Total!E300 | G16: =Total!F300 | H16: =Total!G300 | I16: =Total!H300 | J16: =Total!I300 | ... O16: =Total!N300
A17: NOVEMBRO | C17: =Total!B331 | D17: =Total!C331 | E17: =Total!D331 | F17: =Total!E331 | G17: =Total!F331 | H17: =Total!G331 | I17: =Total!H331 | J17: =Total!I331 | ... O17: =Total!N331
A18: DEZEMBRO | C18: =Total!B362 | D18: =Total!C362 | E18: =Total!D362 | F18: =Total!E362 | G18: =Total!F362 | H18: =Total!G362 | I18: =Total!H362 | J18: =Total!I362 | ... O18: =Total!N362
A19: Total | C19: =SUM(C7:C18) | D19: =SUM(D7:D18) | E19: =SUM(E7:E18) | F19: =SUM(F7:F18) | G19: =SUM(G7:G18) | H19: =SUM(H7:H18) | I19: =SUM(I7:I18) | J19: =SUM(J7:J18) | ... O19: =SUM(O7:O18)
B23: Dif: | G23: =SUM(C19:E19) | H23: =G23-J4

Sheet PETROBRAS
A1: INTERNAÇÕES HOSPITALARES - ESTUDO CUSTO/RECEITA POR CONVÊNIO - ANO 2019
A3: PETROBRAS
D5: INTERNAÇÕES - | G5: ='[13]intern. diaria convenio'!$O$29 | H5: DIÁRIAS - | J5: ='[13]intern. diaria convenio'!$O$74
A6: CONVÊNIO | C6: DIÁRIAS COBRADAS | G6: MAT/MED | I6: TAXAS | K6: DIÁRIAS | M6: TOTAL
C7: PRIV. | D7: SEMI-P | E7: UTI | F7: UCTI | G7: T. CUSTO | H7: T. VENDA | I7: T. CUSTO | J7: T. VENDA | K7: T. CUSTO | L7: T. VENDA | M7: T. CUSTO | N7: T. VENDA | O7: RESULTADO
A8: JANEIRO | C8: =Total!B23 | D8: =Total!C23 | E8: =Total!D23 | F8: =Total!E23 | G8: =Total!F23 | H8: =Total!G23 | I8: =Total!H23 | J8: =Total!I23 | ... O8: =Total!N23
A9: FEVEREIRO | C9: =Total!B54 | D9: =Total!C54 | E9: =Total!D54 | F9: =Total!E54 | G9: =Total!F54 | H9: =Total!G54 | I9: =Total!H54 | J9: =Total!I54 | ... O9: =Total!N54
A10: MARÇO | C10: =Total!B85 | D10: =Total!C85 | E10: =Total!D85 | F10: =Total!E85 | G10: =Total!F85 | H10: =Total!G85 | I10: =Total!H85 | J10: =Total!I85 | ... O10: =Total!N85
A11: ABRIL | C11: =Total!B116 | D11: =Total!C116 | E11: =Total!D116 | F11: =Total!E116 | G11: =Total!F116 | H11: =Total!G116 | I11: =Total!H116 | J11: =Total!I116 | ... O11: =Total!N116
A12: MAIO | C12: =Total!B147 | D12: =Total!C147 | E12: =Total!D147 | F12: =Total!E147 | G12: =Total!F147 | H12: =Total!G147 | I12: =Total!H147 | J12: =Total!I147 | ... O12: =Total!N147
A13: JUNHO | C13: =Total!B178 | D13: =Total!C178 | E13: =Total!D178 | F13: =Total!E178 | G13: =Total!F178 | H13: =Total!G178 | I13: =Total!H178 | J13: =Total!I178 | ... O13: =Total!N178
A14: JULHO | C14: =Total!B209 | D14: =Total!C209 | E14: =Total!D209 | F14: =Total!E209 | G14: =Total!F209 | H14: =Total!G209 | I14: =Total!H209 | J14: =Total!I209 | ... O14: =Total!N209
A15: AGOSTO | C15: =Total!B240 | D15: =Total!C240 | E15: =Total!D240 | F15: =Total!E240 | G15: =Total!F240 | H15: =Total!G240 | I15: =Total!H240 | J15: =Total!I240 | ... O15: =Total!N240
A16: SETEMBRO | C16: =Total!B271 | D16: =Total!C271 | E16: =Total!D271 | F16: =Total!E271 | G16: =Total!F271 | H16: =Total!G271 | I16: =Total!H271 | J16: =Total!I271 | ... O16: =Total!N271
A17: OUTUBRO | C17: =Total!B302 | D17: =Total!C302 | E17: =Total!D302 | F17: =Total!E302 | G17: =Total!F302 | H17: =Total!G302 | I17: =Total!H302 | J17: =Total!I302 | ... O17: =Total!N302
A18: NOVEMBRO | C18: =Total!B333 | D18: =Total!C333 | E18: =Total!D333 | F18: =Total!E333 | G18: =Total!F333 | H18: =Total!G333 | I18: =Total!H333 | J18: =Total!I333 | ... O18: =Total!N333
A19: DEZEMBRO | C19: =Total!B364 | D19: =Total!C364 | E19: =Total!D364 | F19: =Total!E364 | G19: =Total!F364 | H19: =Total!G364 | I19: =Total!H364 | J19: =Total!I364 | ... O19: =Total!N364
A20: Total | C20: =SUM(C8:C19) | D20: =SUM(D8:D19) | E20: =SUM(E8:E19) | F20: =SUM(F8:F19) | G20: =SUM(G8:G19) | H20: =SUM(H8:H19) | I20: =SUM(I8:I19) | J20: =SUM(J8:J19) | ... O20: =SUM(O8:O19)
B24: Dif: | G24: =SUM(C20:E20) | H24: =G24-J5

Sheet SENRGISUL
A1: INTERNAÇÕES HOSPITALARES - ESTUDO CUSTO/RECEITA POR CONVÊNIO - ANO 2017
A3: SENERGISUL
D4: INTERNAÇÕES - | G4: ='[11]intern. diaria convenio'!$O$33 | H4: DIÁRIAS - | J4: ='[11]intern. diaria convenio'!$O$78
A5: CONVÊNIO | C5: DIÁRIAS COBRADAS | G5: MAT/MED | I5: DIÁRIAS | K5: TAXAS | M5: TOTAL
C6: PRIV. | D6: SEMI-P | E6: UTI | F6: UCTI | G6: T. CUSTO | H6: T. VENDA | I6: T. CUSTO | J6: T. VENDA | K6: T. CUSTO | L6: T. VENDA | M6: T. CUSTO | N6: T. VENDA | O6: RESULTADO
A7: JANEIRO | C7: =Total!B27 | D7: =Total!C27 | E7: =Total!D27 | F7: =Total!E27 | G7: =Total!F27 | H7: =Total!G27 | I7: =Total!H27 | J7: =Total!I27 | ... O7: =Total!N27
A8: FEVEREIRO | C8: =Total!B58 | D8: =Total!C58 | E8: =Total!D58 | F8: =Total!E58 | G8: =Total!F58 | H8: =Total!G58 | I8: =Total!H58 | J8: =Total!I58 | ... O8: =Total!N58
A9: MARÇO | C9: =Total!#REF! | D9: =Total!C89 | E9: =Total!D89 | F9: =Total!E89 | G9: =Total!F89 | H9: =Total!G89 | I9: =Total!H89 | J9: =Total!I89 | K9: =Total!J89 | ... O9: =Total!N89
A10: ABRIL | C10: =Total!#REF! | D10: =Total!C120 | E10: =Total!D120 | F10: =Total!E120 | G10: =Total!F120 | H10: =Total!G120 | I10: =Total!H120 | J10: =Total!I120 | K10: =Total!J120 | ... O10: =Total!N120
A11: MAIO | C11: =Total!B151 | D11: =Total!C151 | E11: =Total!D151 | F11: =Total!E151 | G11: =Total!F151 | H11: =Total!G151 | I11: =Total!H151 | J11: =Total!I151 | ... O11: =Total!N151
A12: JUNHO | C12: =Total!B182 | D12: =Total!C182 | E12: =Total!D182 | F12: =Total!E182 | G12: =Total!F182 | H12: =Total!G182 | I12: =Total!H182 | J12: =Total!I182 | ... O12: =Total!N182
A13: JULHO | C13: =Total!B213 | D13: =Total!C213 | E13: =Total!D213 | F13: =Total!E213 | G13: =Total!F213 | H13: =Total!G213 | I13: =Total!H213 | J13: =Total!I213 | ... O13: =Total!N213
A14: AGOSTO | C14: =Total!B244 | D14: =Total!C244 | E14: =Total!D244 | F14: =Total!E244 | G14: =Total!F244 | H14: =Total!G244 | I14: =Total!H244 | J14: =Total!I244 | ... O14: =Total!N244
A15: SETEMBRO | C15: =Total!B275 | D15: =Total!C275 | E15: =Total!D275 | F15: =Total!E275 | G15: =Total!F275 | H15: =Total!G275 | I15: =Total!H275 | J15: =Total!I275 | ... O15: =Total!N275
A16: OUTUBRO | C16: =Total!B306 | D16: =Total!C306 | E16: =Total!D306 | F16: =Total!E306 | G16: =Total!F306 | H16: =Total!G306 | I16: =Total!H306 | J16: =Total!I306 | ... O16: =Total!N306
A17: NOVEMBRO | C17: =Total!B337 | D17: =Total!C337 | E17: =Total!D337 | F17: =Total!E337 | G17: =Total!F337 | H17: =Total!G337 | I17: =Total!H337 | J17: =Total!I337 | ... O17: =Total!N337
A18: DEZEMBRO | C18: =Total!B368 | D18: =Total!C368 | E18: =Total!D368 | F18: =Total!E368 | G18: =Total!F368 | H18: =Total!G368 | I18: =Total!H368 | J18: =Total!I368 | ... O18: =Total!N368
A19: Total | C19: =SUM(C7:C18) | D19: =SUM(D7:D18) | E19: =SUM(E7:E18) | F19: =SUM(F7:F18) | G19: =SUM(G7:G18) | H19: =SUM(H7:H18) | I19: =SUM(I7:I18) | J19: =SUM(J7:J18) | ... O19: =SUM(O7:O18)
B23: Dif: | G23: =SUM(C19:E19) | H23: =G23-J4

Sheet Plan1
